Lab8/Ejercicio1/Ejercicio1.v
module contador12( input [11:0]d,
                   input clk, rst, load, enabled,
                   output reg [11:0] contador);

always @ (posedge clk)
begin
    if (rst)
        contador <= 12'b0;
    else if (load)
        contador <= d;
    if (enabled)
    begin
        if (contador == 12'd4095)
        contador <= 12'b0;
    else
        contador <= contador + 12'b000000000001;
    end
end


endmodule

Lab8/Ejercicio1/Ejercicio1_tb.v
module testbench();

reg [11:0] d;
reg clk;
reg rst;
reg load;
reg enabled;
wire [11:0] contador;



contador12 C1(d, clk, rst, load,enabled, contador);

initial begin
clk = 1;
rst = 0;
#2 rst = 1;
#2 rst = 0;
#2 load = 0;
#2 enabled = 1;
#2 d = 12'b101;
#8190
rst = 1;
#1 rst = 0;
load = 1;

#50 enabled = 0;
#500 $finish;
end

always
#1 clk = !clk;




initial begin
       $dumpfile("Ejercicio1_tb.vcd");
       $dumpvars(0,testbench);
   end
endmodule

Lab8/Ejercicio1/Ejercicio1_tb.vcd
$date
	Sat Oct 24 10:20:14 2020
$end
$version
	Icarus Verilog
$end
$timescale
	1ps
$end
$scope module testbench $end
$var wire 12 ! contador [11:0] $end
$var reg 1 " clk $end
$var reg 12 # d [11:0] $end
$var reg 1 $ enabled $end
$var reg 1 % load $end
$var reg 1 & rst $end
$scope module C1 $end
$var wire 1 " clk $end
$var wire 12 ' d [11:0] $end
$var wire 1 $ enabled $end
$var wire 1 % load $end
$var wire 1 & rst $end
$var reg 12 ( contador [11:0] $end
$upscope $end
$upscope $end
$enddefinitions $end
#0
$dumpvars
bx (
bx '
0&
x%
x$
bx #
1"
bx !
$end
#1
0"
#2
b0 !
b0 (
1"
1&
#3
0"
#4
1"
0&
#5
0"
#6
1"
0%
#7
0"
#8
b1 !
b1 (
1"
1$
#9
0"
#10
b10 !
b10 (
1"
b101 #
b101 '
#11
0"
#12
b11 !
b11 (
1"
#13
0"
#14
b100 !
b100 (
1"
#15
0"
#16
b101 !
b101 (
1"
#17
0"
#18
b110 !
b110 (
1"
#19
0"
#20
b111 !
b111 (
1"
#21
0"
#22
b1000 !
b1000 (
1"
#23
0"
#24
b1001 !
b1001 (
1"
#25
0"
#26
b1010 !
b1010 (
1"
#27
0"
#28
b1011 !
b1011 (
1"
#29
0"
#30
b1100 !
b1100 (
1"
#31
0"
#32
b1101 !
b1101 (
1"
#33
0"
#34
b1110 !
b1110 (
1"
#35
0"
#36
b1111 !
b1111 (
1"
#37
0"
#38
b10000 !
b10000 (
1"
#39
0"
#40
b10001 !
b10001 (
1"
#41
0"
#42
b10010 !
b10010 (
1"
#43
0"
#44
b10011 !
b10011 (
1"
#45
0"
#46
b10100 !
b10100 (
1"
#47
0"
#48
b10101 !
b10101 (
1"
#49
0"
#50
b10110 !
b10110 (
1"
#51
0"
#52
b10111 !
b10111 (
1"
#53
0"
#54
b11000 !
b11000 (
1"
#55
0"
#56
b11001 !
b11001 (
1"
#57
0"
#58
b11010 !
b11010 (
1"
#59
0"
#60
b11011 !
b11011 (
1"
#61
0"
#62
b11100 !
b11100 (
1"
#63
0"
#64
b11101 !
b11101 (
1"
#65
0"
#66
b11110 !
b11110 (
1"
#67
0"
#68
b11111 !
b11111 (
1"
#69
0"
#70
b100000 !
b100000 (
1"
#71
0"
#72
b100001 !
b100001 (
1"
#73
0"
#74
b100010 !
b100010 (
1"
#75
0"
#76
b100011 !
b100011 (
1"
#77
0"
#78
b100100 !
b100100 (
1"
#79
0"
#80
b100101 !
b100101 (
1"
#81
0"
#82
b100110 !
b100110 (
1"
#83
0"
#84
b100111 !
b100111 (
1"
#85
0"
#86
b101000 !
b101000 (
1"
#87
0"
#88
b101001 !
b101001 (
1"
#89
0"
#90
b101010 !
b101010 (
1"
#91
0"
#92
b101011 !
b101011 (
1"
#93
0"
#94
b101100 !
b101100 (
1"
#95
0"
#96
b101101 !
b101101 (
1"
#97
0"
#98
b101110 !
b101110 (
1"
#99
0"
#100
b101111 !
b101111 (
1"
#101
0"
#102
b110000 !
b110000 (
1"
#103
0"
#104
b110001 !
b110001 (
1"
#105
0"
#106
b110010 !
b110010 (
1"
#107
0"
#108
b110011 !
b110011 (
1"
#109
0"
#110
b110100 !
b110100 (
1"
#111
0"
#112
b110101 !
b110101 (
1"
#113
0"
#114
b110110 !
b110110 (
1"
#115
0"
#116
b110111 !
b110111 (
1"
#117
0"
#118
b111000 !
b111000 (
1"
#119
0"
#120
b111001 !
b111001 (
1"
#121
0"
#122
b111010 !
b111010 (
1"
#123
0"
#124
b111011 !
b111011 (
1"
#125
0"
#126
b111100 !
b111100 (
1"
#127
0"
#128
b111101 !
b111101 (
1"
#129
0"
#130
b111110 !
b111110 (
1"
#131
0"
#132
b111111 !
b111111 (
1"
#133
0"
#134
b1000000 !
b1000000 (
1"
#135
0"
#136
b1000001 !
b1000001 (
1"
#137
0"
#138
b1000010 !
b1000010 (
1"
#139
0"
#140
b1000011 !
b1000011 (
1"
#141
0"
#142
b1000100 !
b1000100 (
1"
#143
0"
#144
b1000101 !
b1000101 (
1"
#145
0"
#146
b1000110 !
b1000110 (
1"
#147
0"
#148
b1000111 !
b1000111 (
1"
#149
0"
#150
b1001000 !
b1001000 (
1"
#151
0"
#152
b1001001 !
b1001001 (
1"
#153
0"
#154
b1001010 !
b1001010 (
1"
#155
0"
#156
b1001011 !
b1001011 (
1"
#157
0"
#158
b1001100 !
b1001100 (
1"
#159
0"
#160
b1001101 !
b1001101 (
1"
#161
0"
#162
b1001110 !
b1001110 (
1"
#163
0"
#164
b1001111 !
b1001111 (
1"
#165
0"
#166
b1010000 !
b1010000 (
1"
#167
0"
#168
b1010001 !
b1010001 (
1"
#169
0"
#170
b1010010 !
b1010010 (
1"
#171
0"
#172
b1010011 !
b1010011 (
1"
#173
0"
#174
b1010100 !
b1010100 (
1"
#175
0"
#176
b1010101 !
b1010101 (
1"
#177
0"
#178
b1010110 !
b1010110 (
1"
#179
0"
#180
b1010111 !
b1010111 (
1"
#181
0"
#182
b1011000 !
b1011000 (
1"
#183
0"
#184
b1011001 !
b1011001 (
1"
#185
0"
#186
b1011010 !
b1011010 (
1"
#187
0"
#188
b1011011 !
b1011011 (
1"
#189
0"
#190
b1011100 !
b1011100 (
1"
#191
0"
#192
b1011101 !
b1011101 (
1"
#193
0"
#194
b1011110 !
b1011110 (
1"
#195
0"
#196
b1011111 !
b1011111 (
1"
#197
0"
#198
b1100000 !
b1100000 (
1"
#199
0"
#200
b1100001 !
b1100001 (
1"
#201
0"
#202
b1100010 !
b1100010 (
1"
#203
0"
#204
b1100011 !
b1100011 (
1"
#205
0"
#206
b1100100 !
b1100100 (
1"
#207
0"
#208
b1100101 !
b1100101 (
1"
#209
0"
#210
b1100110 !
b1100110 (
1"
#211
0"
#212
b1100111 !
b1100111 (
1"
#213
0"
#214
b1101000 !
b1101000 (
1"
#215
0"
#216
b1101001 !
b1101001 (
1"
#217
0"
#218
b1101010 !
b1101010 (
1"
#219
0"
#220
b1101011 !
b1101011 (
1"
#221
0"
#222
b1101100 !
b1101100 (
1"
#223
0"
#224
b1101101 !
b1101101 (
1"
#225
0"
#226
b1101110 !
b1101110 (
1"
#227
0"
#228
b1101111 !
b1101111 (
1"
#229
0"
#230
b1110000 !
b1110000 (
1"
#231
0"
#232
b1110001 !
b1110001 (
1"
#233
0"
#234
b1110010 !
b1110010 (
1"
#235
0"
#236
b1110011 !
b1110011 (
1"
#237
0"
#238
b1110100 !
b1110100 (
1"
#239
0"
#240
b1110101 !
b1110101 (
1"
#241
0"
#242
b1110110 !
b1110110 (
1"
#243
0"
#244
b1110111 !
b1110111 (
1"
#245
0"
#246
b1111000 !
b1111000 (
1"
#247
0"
#248
b1111001 !
b1111001 (
1"
#249
0"
#250
b1111010 !
b1111010 (
1"
#251
0"
#252
b1111011 !
b1111011 (
1"
#253
0"
#254
b1111100 !
b1111100 (
1"
#255
0"
#256
b1111101 !
b1111101 (
1"
#257
0"
#258
b1111110 !
b1111110 (
1"
#259
0"
#260
b1111111 !
b1111111 (
1"
#261
0"
#262
b10000000 !
b10000000 (
1"
#263
0"
#264
b10000001 !
b10000001 (
1"
#265
0"
#266
b10000010 !
b10000010 (
1"
#267
0"
#268
b10000011 !
b10000011 (
1"
#269
0"
#270
b10000100 !
b10000100 (
1"
#271
0"
#272
b10000101 !
b10000101 (
1"
#273
0"
#274
b10000110 !
b10000110 (
1"
#275
0"
#276
b10000111 !
b10000111 (
1"
#277
0"
#278
b10001000 !
b10001000 (
1"
#279
0"
#280
b10001001 !
b10001001 (
1"
#281
0"
#282
b10001010 !
b10001010 (
1"
#283
0"
#284
b10001011 !
b10001011 (
1"
#285
0"
#286
b10001100 !
b10001100 (
1"
#287
0"
#288
b10001101 !
b10001101 (
1"
#289
0"
#290
b10001110 !
b10001110 (
1"
#291
0"
#292
b10001111 !
b10001111 (
1"
#293
0"
#294
b10010000 !
b10010000 (
1"
#295
0"
#296
b10010001 !
b10010001 (
1"
#297
0"
#298
b10010010 !
b10010010 (
1"
#299
0"
#300
b10010011 !
b10010011 (
1"
#301
0"
#302
b10010100 !
b10010100 (
1"
#303
0"
#304
b10010101 !
b10010101 (
1"
#305
0"
#306
b10010110 !
b10010110 (
1"
#307
0"
#308
b10010111 !
b10010111 (
1"
#309
0"
#310
b10011000 !
b10011000 (
1"
#311
0"
#312
b10011001 !
b10011001 (
1"
#313
0"
#314
b10011010 !
b10011010 (
1"
#315
0"
#316
b10011011 !
b10011011 (
1"
#317
0"
#318
b10011100 !
b10011100 (
1"
#319
0"
#320
b10011101 !
b10011101 (
1"
#321
0"
#322
b10011110 !
b10011110 (
1"
#323
0"
#324
b10011111 !
b10011111 (
1"
#325
0"
#326
b10100000 !
b10100000 (
1"
#327
0"
#328
b10100001 !
b10100001 (
1"
#329
0"
#330
b10100010 !
b10100010 (
1"
#331
0"
#332
b10100011 !
b10100011 (
1"
#333
0"
#334
b10100100 !
b10100100 (
1"
#335
0"
#336
b10100101 !
b10100101 (
1"
#337
0"
#338
b10100110 !
b10100110 (
1"
#339
0"
#340
b10100111 !
b10100111 (
1"
#341
0"
#342
b10101000 !
b10101000 (
1"
#343
0"
#344
b10101001 !
b10101001 (
1"
#345
0"
#346
b10101010 !
b10101010 (
1"
#347
0"
#348
b10101011 !
b10101011 (
1"
#349
0"
#350
b10101100 !
b10101100 (
1"
#351
0"
#352
b10101101 !
b10101101 (
1"
#353
0"
#354
b10101110 !
b10101110 (
1"
#355
0"
#356
b10101111 !
b10101111 (
1"
#357
0"
#358
b10110000 !
b10110000 (
1"
#359
0"
#360
b10110001 !
b10110001 (
1"
#361
0"
#362
b10110010 !
b10110010 (
1"
#363
0"
#364
b10110011 !
b10110011 (
1"
#365
0"
#366
b10110100 !
b10110100 (
1"
#367
0"
#368
b10110101 !
b10110101 (
1"
#369
0"
#370
b10110110 !
b10110110 (
1"
#371
0"
#372
b10110111 !
b10110111 (
1"
#373
0"
#374
b10111000 !
b10111000 (
1"
#375
0"
#376
b10111001 !
b10111001 (
1"
#377
0"
#378
b10111010 !
b10111010 (
1"
#379
0"
#380
b10111011 !
b10111011 (
1"
#381
0"
#382
b10111100 !
b10111100 (
1"
#383
0"
#384
b10111101 !
b10111101 (
1"
#385
0"
#386
b10111110 !
b10111110 (
1"
#387
0"
#388
b10111111 !
b10111111 (
1"
#389
0"
#390
b11000000 !
b11000000 (
1"
#391
0"
#392
b11000001 !
b11000001 (
1"
#393
0"
#394
b11000010 !
b11000010 (
1"
#395
0"
#396
b11000011 !
b11000011 (
1"
#397
0"
#398
b11000100 !
b11000100 (
1"
#399
0"
#400
b11000101 !
b11000101 (
1"
#401
0"
#402
b11000110 !
b11000110 (
1"
#403
0"
#404
b11000111 !
b11000111 (
1"
#405
0"
#406
b11001000 !
b11001000 (
1"
#407
0"
#408
b11001001 !
b11001001 (
1"
#409
0"
#410
b11001010 !
b11001010 (
1"
#411
0"
#412
b11001011 !
b11001011 (
1"
#413
0"
#414
b11001100 !
b11001100 (
1"
#415
0"
#416
b11001101 !
b11001101 (
1"
#417
0"
#418
b11001110 !
b11001110 (
1"
#419
0"
#420
b11001111 !
b11001111 (
1"
#421
0"
#422
b11010000 !
b11010000 (
1"
#423
0"
#424
b11010001 !
b11010001 (
1"
#425
0"
#426
b11010010 !
b11010010 (
1"
#427
0"
#428
b11010011 !
b11010011 (
1"
#429
0"
#430
b11010100 !
b11010100 (
1"
#431
0"
#432
b11010101 !
b11010101 (
1"
#433
0"
#434
b11010110 !
b11010110 (
1"
#435
0"
#436
b11010111 !
b11010111 (
1"
#437
0"
#438
b11011000 !
b11011000 (
1"
#439
0"
#440
b11011001 !
b11011001 (
1"
#441
0"
#442
b11011010 !
b11011010 (
1"
#443
0"
#444
b11011011 !
b11011011 (
1"
#445
0"
#446
b11011100 !
b11011100 (
1"
#447
0"
#448
b11011101 !
b11011101 (
1"
#449
0"
#450
b11011110 !
b11011110 (
1"
#451
0"
#452
b11011111 !
b11011111 (
1"
#453
0"
#454
b11100000 !
b11100000 (
1"
#455
0"
#456
b11100001 !
b11100001 (
1"
#457
0"
#458
b11100010 !
b11100010 (
1"
#459
0"
#460
b11100011 !
b11100011 (
1"
#461
0"
#462
b11100100 !
b11100100 (
1"
#463
0"
#464
b11100101 !
b11100101 (
1"
#465
0"
#466
b11100110 !
b11100110 (
1"
#467
0"
#468
b11100111 !
b11100111 (
1"
#469
0"
#470
b11101000 !
b11101000 (
1"
#471
0"
#472
b11101001 !
b11101001 (
1"
#473
0"
#474
b11101010 !
b11101010 (
1"
#475
0"
#476
b11101011 !
b11101011 (
1"
#477
0"
#478
b11101100 !
b11101100 (
1"
#479
0"
#480
b11101101 !
b11101101 (
1"
#481
0"
#482
b11101110 !
b11101110 (
1"
#483
0"
#484
b11101111 !
b11101111 (
1"
#485
0"
#486
b11110000 !
b11110000 (
1"
#487
0"
#488
b11110001 !
b11110001 (
1"
#489
0"
#490
b11110010 !
b11110010 (
1"
#491
0"
#492
b11110011 !
b11110011 (
1"
#493
0"
#494
b11110100 !
b11110100 (
1"
#495
0"
#496
b11110101 !
b11110101 (
1"
#497
0"
#498
b11110110 !
b11110110 (
1"
#499
0"
#500
b11110111 !
b11110111 (
1"
#501
0"
#502
b11111000 !
b11111000 (
1"
#503
0"
#504
b11111001 !
b11111001 (
1"
#505
0"
#506
b11111010 !
b11111010 (
1"
#507
0"
#508
b11111011 !
b11111011 (
1"
#509
0"
#510
b11111100 !
b11111100 (
1"
#511
0"
#512
b11111101 !
b11111101 (
1"
#513
0"
#514
b11111110 !
b11111110 (
1"
#515
0"
#516
b11111111 !
b11111111 (
1"
#517
0"
#518
b100000000 !
b100000000 (
1"
#519
0"
#520
b100000001 !
b100000001 (
1"
#521
0"
#522
b100000010 !
b100000010 (
1"
#523
0"
#524
b100000011 !
b100000011 (
1"
#525
0"
#526
b100000100 !
b100000100 (
1"
#527
0"
#528
b100000101 !
b100000101 (
1"
#529
0"
#530
b100000110 !
b100000110 (
1"
#531
0"
#532
b100000111 !
b100000111 (
1"
#533
0"
#534
b100001000 !
b100001000 (
1"
#535
0"
#536
b100001001 !
b100001001 (
1"
#537
0"
#538
b100001010 !
b100001010 (
1"
#539
0"
#540
b100001011 !
b100001011 (
1"
#541
0"
#542
b100001100 !
b100001100 (
1"
#543
0"
#544
b100001101 !
b100001101 (
1"
#545
0"
#546
b100001110 !
b100001110 (
1"
#547
0"
#548
b100001111 !
b100001111 (
1"
#549
0"
#550
b100010000 !
b100010000 (
1"
#551
0"
#552
b100010001 !
b100010001 (
1"
#553
0"
#554
b100010010 !
b100010010 (
1"
#555
0"
#556
b100010011 !
b100010011 (
1"
#557
0"
#558
b100010100 !
b100010100 (
1"
#559
0"
#560
b100010101 !
b100010101 (
1"
#561
0"
#562
b100010110 !
b100010110 (
1"
#563
0"
#564
b100010111 !
b100010111 (
1"
#565
0"
#566
b100011000 !
b100011000 (
1"
#567
0"
#568
b100011001 !
b100011001 (
1"
#569
0"
#570
b100011010 !
b100011010 (
1"
#571
0"
#572
b100011011 !
b100011011 (
1"
#573
0"
#574
b100011100 !
b100011100 (
1"
#575
0"
#576
b100011101 !
b100011101 (
1"
#577
0"
#578
b100011110 !
b100011110 (
1"
#579
0"
#580
b100011111 !
b100011111 (
1"
#581
0"
#582
b100100000 !
b100100000 (
1"
#583
0"
#584
b100100001 !
b100100001 (
1"
#585
0"
#586
b100100010 !
b100100010 (
1"
#587
0"
#588
b100100011 !
b100100011 (
1"
#589
0"
#590
b100100100 !
b100100100 (
1"
#591
0"
#592
b100100101 !
b100100101 (
1"
#593
0"
#594
b100100110 !
b100100110 (
1"
#595
0"
#596
b100100111 !
b100100111 (
1"
#597
0"
#598
b100101000 !
b100101000 (
1"
#599
0"
#600
b100101001 !
b100101001 (
1"
#601
0"
#602
b100101010 !
b100101010 (
1"
#603
0"
#604
b100101011 !
b100101011 (
1"
#605
0"
#606
b100101100 !
b100101100 (
1"
#607
0"
#608
b100101101 !
b100101101 (
1"
#609
0"
#610
b100101110 !
b100101110 (
1"
#611
0"
#612
b100101111 !
b100101111 (
1"
#613
0"
#614
b100110000 !
b100110000 (
1"
#615
0"
#616
b100110001 !
b100110001 (
1"
#617
0"
#618
b100110010 !
b100110010 (
1"
#619
0"
#620
b100110011 !
b100110011 (
1"
#621
0"
#622
b100110100 !
b100110100 (
1"
#623
0"
#624
b100110101 !
b100110101 (
1"
#625
0"
#626
b100110110 !
b100110110 (
1"
#627
0"
#628
b100110111 !
b100110111 (
1"
#629
0"
#630
b100111000 !
b100111000 (
1"
#631
0"
#632
b100111001 !
b100111001 (
1"
#633
0"
#634
b100111010 !
b100111010 (
1"
#635
0"
#636
b100111011 !
b100111011 (
1"
#637
0"
#638
b100111100 !
b100111100 (
1"
#639
0"
#640
b100111101 !
b100111101 (
1"
#641
0"
#642
b100111110 !
b100111110 (
1"
#643
0"
#644
b100111111 !
b100111111 (
1"
#645
0"
#646
b101000000 !
b101000000 (
1"
#647
0"
#648
b101000001 !
b101000001 (
1"
#649
0"
#650
b101000010 !
b101000010 (
1"
#651
0"
#652
b101000011 !
b101000011 (
1"
#653
0"
#654
b101000100 !
b101000100 (
1"
#655
0"
#656
b101000101 !
b101000101 (
1"
#657
0"
#658
b101000110 !
b101000110 (
1"
#659
0"
#660
b101000111 !
b101000111 (
1"
#661
0"
#662
b101001000 !
b101001000 (
1"
#663
0"
#664
b101001001 !
b101001001 (
1"
#665
0"
#666
b101001010 !
b101001010 (
1"
#667
0"
#668
b101001011 !
b101001011 (
1"
#669
0"
#670
b101001100 !
b101001100 (
1"
#671
0"
#672
b101001101 !
b101001101 (
1"
#673
0"
#674
b101001110 !
b101001110 (
1"
#675
0"
#676
b101001111 !
b101001111 (
1"
#677
0"
#678
b101010000 !
b101010000 (
1"
#679
0"
#680
b101010001 !
b101010001 (
1"
#681
0"
#682
b101010010 !
b101010010 (
1"
#683
0"
#684
b101010011 !
b101010011 (
1"
#685
0"
#686
b101010100 !
b101010100 (
1"
#687
0"
#688
b101010101 !
b101010101 (
1"
#689
0"
#690
b101010110 !
b101010110 (
1"
#691
0"
#692
b101010111 !
b101010111 (
1"
#693
0"
#694
b101011000 !
b101011000 (
1"
#695
0"
#696
b101011001 !
b101011001 (
1"
#697
0"
#698
b101011010 !
b101011010 (
1"
#699
0"
#700
b101011011 !
b101011011 (
1"
#701
0"
#702
b101011100 !
b101011100 (
1"
#703
0"
#704
b101011101 !
b101011101 (
1"
#705
0"
#706
b101011110 !
b101011110 (
1"
#707
0"
#708
b101011111 !
b101011111 (
1"
#709
0"
#710
b101100000 !
b101100000 (
1"
#711
0"
#712
b101100001 !
b101100001 (
1"
#713
0"
#714
b101100010 !
b101100010 (
1"
#715
0"
#716
b101100011 !
b101100011 (
1"
#717
0"
#718
b101100100 !
b101100100 (
1"
#719
0"
#720
b101100101 !
b101100101 (
1"
#721
0"
#722
b101100110 !
b101100110 (
1"
#723
0"
#724
b101100111 !
b101100111 (
1"
#725
0"
#726
b101101000 !
b101101000 (
1"
#727
0"
#728
b101101001 !
b101101001 (
1"
#729
0"
#730
b101101010 !
b101101010 (
1"
#731
0"
#732
b101101011 !
b101101011 (
1"
#733
0"
#734
b101101100 !
b101101100 (
1"
#735
0"
#736
b101101101 !
b101101101 (
1"
#737
0"
#738
b101101110 !
b101101110 (
1"
#739
0"
#740
b101101111 !
b101101111 (
1"
#741
0"
#742
b101110000 !
b101110000 (
1"
#743
0"
#744
b101110001 !
b101110001 (
1"
#745
0"
#746
b101110010 !
b101110010 (
1"
#747
0"
#748
b101110011 !
b101110011 (
1"
#749
0"
#750
b101110100 !
b101110100 (
1"
#751
0"
#752
b101110101 !
b101110101 (
1"
#753
0"
#754
b101110110 !
b101110110 (
1"
#755
0"
#756
b101110111 !
b101110111 (
1"
#757
0"
#758
b101111000 !
b101111000 (
1"
#759
0"
#760
b101111001 !
b101111001 (
1"
#761
0"
#762
b101111010 !
b101111010 (
1"
#763
0"
#764
b101111011 !
b101111011 (
1"
#765
0"
#766
b101111100 !
b101111100 (
1"
#767
0"
#768
b101111101 !
b101111101 (
1"
#769
0"
#770
b101111110 !
b101111110 (
1"
#771
0"
#772
b101111111 !
b101111111 (
1"
#773
0"
#774
b110000000 !
b110000000 (
1"
#775
0"
#776
b110000001 !
b110000001 (
1"
#777
0"
#778
b110000010 !
b110000010 (
1"
#779
0"
#780
b110000011 !
b110000011 (
1"
#781
0"
#782
b110000100 !
b110000100 (
1"
#783
0"
#784
b110000101 !
b110000101 (
1"
#785
0"
#786
b110000110 !
b110000110 (
1"
#787
0"
#788
b110000111 !
b110000111 (
1"
#789
0"
#790
b110001000 !
b110001000 (
1"
#791
0"
#792
b110001001 !
b110001001 (
1"
#793
0"
#794
b110001010 !
b110001010 (
1"
#795
0"
#796
b110001011 !
b110001011 (
1"
#797
0"
#798
b110001100 !
b110001100 (
1"
#799
0"
#800
b110001101 !
b110001101 (
1"
#801
0"
#802
b110001110 !
b110001110 (
1"
#803
0"
#804
b110001111 !
b110001111 (
1"
#805
0"
#806
b110010000 !
b110010000 (
1"
#807
0"
#808
b110010001 !
b110010001 (
1"
#809
0"
#810
b110010010 !
b110010010 (
1"
#811
0"
#812
b110010011 !
b110010011 (
1"
#813
0"
#814
b110010100 !
b110010100 (
1"
#815
0"
#816
b110010101 !
b110010101 (
1"
#817
0"
#818
b110010110 !
b110010110 (
1"
#819
0"
#820
b110010111 !
b110010111 (
1"
#821
0"
#822
b110011000 !
b110011000 (
1"
#823
0"
#824
b110011001 !
b110011001 (
1"
#825
0"
#826
b110011010 !
b110011010 (
1"
#827
0"
#828
b110011011 !
b110011011 (
1"
#829
0"
#830
b110011100 !
b110011100 (
1"
#831
0"
#832
b110011101 !
b110011101 (
1"
#833
0"
#834
b110011110 !
b110011110 (
1"
#835
0"
#836
b110011111 !
b110011111 (
1"
#837
0"
#838
b110100000 !
b110100000 (
1"
#839
0"
#840
b110100001 !
b110100001 (
1"
#841
0"
#842
b110100010 !
b110100010 (
1"
#843
0"
#844
b110100011 !
b110100011 (
1"
#845
0"
#846
b110100100 !
b110100100 (
1"
#847
0"
#848
b110100101 !
b110100101 (
1"
#849
0"
#850
b110100110 !
b110100110 (
1"
#851
0"
#852
b110100111 !
b110100111 (
1"
#853
0"
#854
b110101000 !
b110101000 (
1"
#855
0"
#856
b110101001 !
b110101001 (
1"
#857
0"
#858
b110101010 !
b110101010 (
1"
#859
0"
#860
b110101011 !
b110101011 (
1"
#861
0"
#862
b110101100 !
b110101100 (
1"
#863
0"
#864
b110101101 !
b110101101 (
1"
#865
0"
#866
b110101110 !
b110101110 (
1"
#867
0"
#868
b110101111 !
b110101111 (
1"
#869
0"
#870
b110110000 !
b110110000 (
1"
#871
0"
#872
b110110001 !
b110110001 (
1"
#873
0"
#874
b110110010 !
b110110010 (
1"
#875
0"
#876
b110110011 !
b110110011 (
1"
#877
0"
#878
b110110100 !
b110110100 (
1"
#879
0"
#880
b110110101 !
b110110101 (
1"
#881
0"
#882
b110110110 !
b110110110 (
1"
#883
0"
#884
b110110111 !
b110110111 (
1"
#885
0"
#886
b110111000 !
b110111000 (
1"
#887
0"
#888
b110111001 !
b110111001 (
1"
#889
0"
#890
b110111010 !
b110111010 (
1"
#891
0"
#892
b110111011 !
b110111011 (
1"
#893
0"
#894
b110111100 !
b110111100 (
1"
#895
0"
#896
b110111101 !
b110111101 (
1"
#897
0"
#898
b110111110 !
b110111110 (
1"
#899
0"
#900
b110111111 !
b110111111 (
1"
#901
0"
#902
b111000000 !
b111000000 (
1"
#903
0"
#904
b111000001 !
b111000001 (
1"
#905
0"
#906
b111000010 !
b111000010 (
1"
#907
0"
#908
b111000011 !
b111000011 (
1"
#909
0"
#910
b111000100 !
b111000100 (
1"
#911
0"
#912
b111000101 !
b111000101 (
1"
#913
0"
#914
b111000110 !
b111000110 (
1"
#915
0"
#916
b111000111 !
b111000111 (
1"
#917
0"
#918
b111001000 !
b111001000 (
1"
#919
0"
#920
b111001001 !
b111001001 (
1"
#921
0"
#922
b111001010 !
b111001010 (
1"
#923
0"
#924
b111001011 !
b111001011 (
1"
#925
0"
#926
b111001100 !
b111001100 (
1"
#927
0"
#928
b111001101 !
b111001101 (
1"
#929
0"
#930
b111001110 !
b111001110 (
1"
#931
0"
#932
b111001111 !
b111001111 (
1"
#933
0"
#934
b111010000 !
b111010000 (
1"
#935
0"
#936
b111010001 !
b111010001 (
1"
#937
0"
#938
b111010010 !
b111010010 (
1"
#939
0"
#940
b111010011 !
b111010011 (
1"
#941
0"
#942
b111010100 !
b111010100 (
1"
#943
0"
#944
b111010101 !
b111010101 (
1"
#945
0"
#946
b111010110 !
b111010110 (
1"
#947
0"
#948
b111010111 !
b111010111 (
1"
#949
0"
#950
b111011000 !
b111011000 (
1"
#951
0"
#952
b111011001 !
b111011001 (
1"
#953
0"
#954
b111011010 !
b111011010 (
1"
#955
0"
#956
b111011011 !
b111011011 (
1"
#957
0"
#958
b111011100 !
b111011100 (
1"
#959
0"
#960
b111011101 !
b111011101 (
1"
#961
0"
#962
b111011110 !
b111011110 (
1"
#963
0"
#964
b111011111 !
b111011111 (
1"
#965
0"
#966
b111100000 !
b111100000 (
1"
#967
0"
#968
b111100001 !
b111100001 (
1"
#969
0"
#970
b111100010 !
b111100010 (
1"
#971
0"
#972
b111100011 !
b111100011 (
1"
#973
0"
#974
b111100100 !
b111100100 (
1"
#975
0"
#976
b111100101 !
b111100101 (
1"
#977
0"
#978
b111100110 !
b111100110 (
1"
#979
0"
#980
b111100111 !
b111100111 (
1"
#981
0"
#982
b111101000 !
b111101000 (
1"
#983
0"
#984
b111101001 !
b111101001 (
1"
#985
0"
#986
b111101010 !
b111101010 (
1"
#987
0"
#988
b111101011 !
b111101011 (
1"
#989
0"
#990
b111101100 !
b111101100 (
1"
#991
0"
#992
b111101101 !
b111101101 (
1"
#993
0"
#994
b111101110 !
b111101110 (
1"
#995
0"
#996
b111101111 !
b111101111 (
1"
#997
0"
#998
b111110000 !
b111110000 (
1"
#999
0"
#1000
b111110001 !
b111110001 (
1"
#1001
0"
#1002
b111110010 !
b111110010 (
1"
#1003
0"
#1004
b111110011 !
b111110011 (
1"
#1005
0"
#1006
b111110100 !
b111110100 (
1"
#1007
0"
#1008
b111110101 !
b111110101 (
1"
#1009
0"
#1010
b111110110 !
b111110110 (
1"
#1011
0"
#1012
b111110111 !
b111110111 (
1"
#1013
0"
#1014
b111111000 !
b111111000 (
1"
#1015
0"
#1016
b111111001 !
b111111001 (
1"
#1017
0"
#1018
b111111010 !
b111111010 (
1"
#1019
0"
#1020
b111111011 !
b111111011 (
1"
#1021
0"
#1022
b111111100 !
b111111100 (
1"
#1023
0"
#1024
b111111101 !
b111111101 (
1"
#1025
0"
#1026
b111111110 !
b111111110 (
1"
#1027
0"
#1028
b111111111 !
b111111111 (
1"
#1029
0"
#1030
b1000000000 !
b1000000000 (
1"
#1031
0"
#1032
b1000000001 !
b1000000001 (
1"
#1033
0"
#1034
b1000000010 !
b1000000010 (
1"
#1035
0"
#1036
b1000000011 !
b1000000011 (
1"
#1037
0"
#1038
b1000000100 !
b1000000100 (
1"
#1039
0"
#1040
b1000000101 !
b1000000101 (
1"
#1041
0"
#1042
b1000000110 !
b1000000110 (
1"
#1043
0"
#1044
b1000000111 !
b1000000111 (
1"
#1045
0"
#1046
b1000001000 !
b1000001000 (
1"
#1047
0"
#1048
b1000001001 !
b1000001001 (
1"
#1049
0"
#1050
b1000001010 !
b1000001010 (
1"
#1051
0"
#1052
b1000001011 !
b1000001011 (
1"
#1053
0"
#1054
b1000001100 !
b1000001100 (
1"
#1055
0"
#1056
b1000001101 !
b1000001101 (
1"
#1057
0"
#1058
b1000001110 !
b1000001110 (
1"
#1059
0"
#1060
b1000001111 !
b1000001111 (
1"
#1061
0"
#1062
b1000010000 !
b1000010000 (
1"
#1063
0"
#1064
b1000010001 !
b1000010001 (
1"
#1065
0"
#1066
b1000010010 !
b1000010010 (
1"
#1067
0"
#1068
b1000010011 !
b1000010011 (
1"
#1069
0"
#1070
b1000010100 !
b1000010100 (
1"
#1071
0"
#1072
b1000010101 !
b1000010101 (
1"
#1073
0"
#1074
b1000010110 !
b1000010110 (
1"
#1075
0"
#1076
b1000010111 !
b1000010111 (
1"
#1077
0"
#1078
b1000011000 !
b1000011000 (
1"
#1079
0"
#1080
b1000011001 !
b1000011001 (
1"
#1081
0"
#1082
b1000011010 !
b1000011010 (
1"
#1083
0"
#1084
b1000011011 !
b1000011011 (
1"
#1085
0"
#1086
b1000011100 !
b1000011100 (
1"
#1087
0"
#1088
b1000011101 !
b1000011101 (
1"
#1089
0"
#1090
b1000011110 !
b1000011110 (
1"
#1091
0"
