Lab6/Ejercicio06/Ejercicio01/Ejercicio01.v
//Ejercicio01 en verilog
module Ejercicio01(input A,B,clk,reset, output y);
    reg [1:0]estado_actual; // el estado actual esta dado en 2 bits
    wire [1:0]estado_siguiente; // igual que el estado siguiente
    wire n1;

    assign n1 = estado_actual[1] & A & B ; //debido a que en esta fsm se podia ver
    //que y era igual a s1, este cable es usado para ambos
    assign estado_siguiente[0]= ~estado_actual[1] & ~estado_actual[0] & A;
    assign estado_siguiente[1]=  n1 | (estado_actual[0] & B);
    assign y = n1;

    always @ (posedge clk, posedge reset) estado_actual <= reset? 2'b00 : estado_siguiente;

endmodule

Lab6/Ejercicio06/Ejercicio01/Ejercicio01_tb.v
module testbench();
    reg A,B;
    reg reset01;
    wire out01;
    reg clk;

     Ejercicio01 E1(A,B,clk,reset01,out01);


    initial clk =0 ;

    initial begin
        reset01=0;
        #1 reset01=1;
        #1 reset01=0;
        #1 A=0; B=0;
        #17 B=1;
        #20 A=1;B=0;
        #100 B=1;
        #20  B=0;
        #40  B=1;
        #20  A=0; B=0;
        #20 $finish;
    end

    always #10 clk= ~clk;

    initial begin
        $dumpfile("Ejercicio01_tb.vcd");
        $dumpvars(0,testbench);
    end

endmodule

Lab6/Ejercicio06/Ejercicio01/ejercicio06_tb.vcd
$date
	Sat Sep 05 20:41:42 2020
$end
$version
	Icarus Verilog
$end
$timescale
	1ps
$end
$scope module testbench $end
$var wire 1 ! out01 $end
$var reg 1 " A $end
$var reg 1 # B $end
$var reg 1 $ clk $end
$var reg 1 % reset01 $end
$scope module E1 $end
$var wire 1 " A $end
$var wire 1 # B $end
$var wire 1 $ clk $end
$var wire 1 & n1 $end
$var wire 1 % reset $end
$var wire 1 ! y $end
$var wire 2 ' estado_siguiente [1:0] $end
$var reg 2 ( estado_actual [1:0] $end
$upscope $end
$upscope $end
$enddefinitions $end
#0
$dumpvars
bx (
bx '
x&
0%
0$
x#
x"
x!
$end
#1
b0x '
0!
0&
b0 (
1%
#2
0%
#3
b0 '
0#
0"
#10
1$
#20
0$
1#
#30
1$
#40
b1 '
0$
0#
1"
#50
b0 '
b1 (
1$
#60
0$
#70
b1 '
b0 (
1$
#80
0$
#90
b0 '
b1 (
1$
#100
0$
#110
b1 '
b0 (
1$
#120
0$
#130
b0 '
b1 (
1$
#140
b10 '
0$
1#
#150
1!
1&
b10 '
b10 (
1$
#160
b0 '
0!
0&
0$
0#
#170
b1 '
b0 (
1$
#180
0$
#190
b0 '
b1 (
1$
#200
b10 '
0$
1#
#210
1!
1&
b10 '
b10 (
1$
#220
b0 '
0!
0&
0$
0#
0"
#230
b0 (
1$
