Lab10/Ejercicio1/Ejercicio1.v
//modulo del programm counter
module pc(input [11:0] valor_load, input load, enablePC, clk, rst, output reg [11:0] pc);

always @(posedge clk, posedge rst)
begin
  if (rst)  begin
    pc <=12'b0;
  end
  if (enablePC & ~rst & ~load) begin
    pc <= pc +1;
  end
  if(load & ~rst & enablePC) begin
    pc <=valor_load;
  end
end
endmodule


module ROM (input [11:0] address, output [7:0]data);

reg [11:0] mem [0:4095]; //memoria de 12 bits, con 8 bits de ancho.
assign data = mem[address];

initial begin
$readmemb("memory.txt", mem);
end

endmodule


module fetch(input [7:0] D, input clk, rst, enableFetch, output reg [3:0] operando, instruccion);
//es un flip flop de 8 bits
always  @(posedge clk, posedge rst)
begin
if (rst) begin
  operando <= 4'b0;
  instruccion <=4'b0;
  end
if(enableFetch & ~rst) begin
  operando <= D[3:0 ];
  instruccion <= D[7:4];
end
end
endmodule

module conexion (input [11:0] valor_load, input clk, rst, enablePCC, enableFetchC, loadC,
                 output [3:0] operandoC, instruccionC, output [7:0] dataC);
//en este modulo se conectan los otros modulos

wire loadC;
wire enablePCC;
wire enableFetchC;
wire clk;
wire rst;
wire [11:0] pcC;
wire [7:0]dataC;
wire [3:0] operandoC;
wire [3:0] instruccionC;


pc PC1(valor_load, loadC, enablePCC, clk, rst, pcC);
ROM r1(pcC, dataC);
fetch F1(dataC, clk, rst, enableFetchC, operandoC, instruccionC);
endmodule // conexion

Lab10/Ejercicio1/Ejercicio1_tb.v
module testbench();

reg [11:0]valor_load;
reg load;
reg enablePC;
reg enableFetch;
reg clk;
reg rst;
wire [11:0]pc;
wire [7:0] program_byte;
wire [3:0] operando;
wire [3:0] instruccion;


conexion C1(valor_load,clk,rst, enablePC, enableFetch,load, operando, instruccion, program_byte);


initial begin
clk = 1;
rst = 1'b1;
valor_load = 12'd0;
#1 rst = 1'b0;
enablePC = 1'b1;
enableFetch = 1'b1;
load = 1'b1;
#2 valor_load = 12'd10;
#1 rst = 0;
#2load = 1'b0;

#1 load = 1'b1; //probando si se vuelve a recargar el valor de load
#1enablePC = 1'b0;    enableFetch = 1'b0;   //probando enables
#10 enablePC = 1'b1;    enableFetch = 1'b1;
valor_load = 12'd0;
load = 1'b0; 


#50 $finish;
end

initial begin

  $dumpfile("Ejercicio1_tb.vcd");
  $dumpvars(0,testbench);
  end

  always
  #1 clk = !clk;


endmodule

Lab10/Ejercicio1/Ejercicio1_tb.vcd
$date
	Sat Nov 07 11:47:27 2020
$end
$version
	Icarus Verilog
$end
$timescale
	1ps
$end
$scope module testbench $end
$var wire 8 ! program_byte [7:0] $end
$var wire 4 " operando [3:0] $end
$var wire 4 # instruccion [3:0] $end
$var reg 1 $ clk $end
$var reg 1 % enableFetch $end
$var reg 1 & enablePC $end
$var reg 1 ' load $end
$var reg 1 ( rst $end
$var reg 12 ) valor_load [11:0] $end
$scope module C1 $end
$var wire 1 $ clk $end
$var wire 1 % enableFetchC $end
$var wire 1 & enablePCC $end
$var wire 1 ' loadC $end
$var wire 1 ( rst $end
$var wire 12 * valor_load [11:0] $end
$var wire 12 + pcC [11:0] $end
$var wire 4 , operandoC [3:0] $end
$var wire 4 - instruccionC [3:0] $end
$var wire 8 . dataC [7:0] $end
$scope module F1 $end
$var wire 1 $ clk $end
$var wire 1 % enableFetch $end
$var wire 1 ( rst $end
$var wire 8 / D [7:0] $end
$var reg 4 0 instruccion [3:0] $end
$var reg 4 1 operando [3:0] $end
$upscope $end
$scope module PC1 $end
$var wire 1 $ clk $end
$var wire 1 & enablePC $end
$var wire 1 ' load $end
$var wire 1 ( rst $end
$var wire 12 2 valor_load [11:0] $end
$var reg 12 3 pc [11:0] $end
$upscope $end
$scope module r1 $end
$var wire 12 4 address [11:0] $end
$var wire 8 5 data [7:0] $end
$upscope $end
$upscope $end
$upscope $end
$enddefinitions $end
#0
$dumpvars
b11000000 5
b0 4
b0 3
b0 2
b0 1
b0 0
b11000000 /
b11000000 .
b0 -
b0 ,
b0 +
b0 *
b0 )
1(
x'
x&
x%
1$
b0 #
b0 "
b11000000 !
$end
#1
0$
1'
1%
1&
0(
#2
b1100 #
b1100 -
b1100 0
1$
#3
0$
b1010 )
b1010 *
b1010 2
#4
b1010 +
b1010 3
b1010 4
1$
#5
0$
#6
b11111111 !
b11111111 .
b11111111 /
b11111111 5
b1011 +
b1011 3
b1011 4
1$
0'
#7
0$
1'
#8
1$
0%
0&
#9
0$
#10
1$
#11
0$
#12
1$
#13
0$
#14
1$
#15
0$
#16
1$
#17
0$
#18
b1 !
b1 .
b1 /
b1 5
b1111 #
b1111 -
b1111 0
b1111 "
b1111 ,
b1111 1
b1100 +
b1100 3
b1100 4
1$
0'
b0 )
b0 *
b0 2
1%
1&
#19
0$
#20
b10111111 !
b10111111 .
b10111111 /
b10111111 5
b1101 +
b1101 3
b1101 4
b0 #
b0 -
b0 0
b1 "
b1 ,
b1 1
1$
#21
0$
#22
b11100000 !
b11100000 .
b11100000 /
b11100000 5
b1011 #
b1011 -
b1011 0
b1111 "
b1111 ,
b1111 1
b1110 +
b1110 3
b1110 4
1$
#23
0$
#24
b11010111 !
b11010111 .
b11010111 /
b11010111 5
b1111 +
b1111 3
b1111 4
b1110 #
b1110 -
b1110 0
b0 "
b0 ,
b0 1
1$
#25
0$
#26
b11010000 !
b11010000 .
b11010000 /
b11010000 5
b1101 #
b1101 -
b1101 0
b111 "
b111 ,
b111 1
b10000 +
b10000 3
b10000 4
1$
#27
0$
#28
b11000111 !
b11000111 .
b11000111 /
b11000111 5
b10001 +
b10001 3
b10001 4
b0 "
b0 ,
b0 1
1$
#29
0$
#30
b11000001 !
b11000001 .
b11000001 /
b11000001 5
b1100 #
b1100 -
b1100 0
b111 "
b111 ,
b111 1
b10010 +
b10010 3
b10010 4
1$
#31
0$
#32
b10000000 !
b10000000 .
b10000000 /
b10000000 5
b10011 +
b10011 3
b10011 4
b1 "
b1 ,
b1 1
1$
#33
0$
#34
b11000000 !
b11000000 .
b11000000 /
b11000000 5
b1000 #
b1000 -
b1000 0
b0 "
b0 ,
b0 1
b10100 +
b10100 3
b10100 4
1$
#35
0$
#36
b11111111 !
b11111111 .
b11111111 /
b11111111 5
b10101 +
b10101 3
b10101 4
b1100 #
b1100 -
b1100 0
1$
#37
0$
#38
b1 !
b1 .
b1 /
b1 5
b1111 #
b1111 -
b1111 0
b1111 "
b1111 ,
b1111 1
b10110 +
b10110 3
b10110 4
1$
#39
0$
#40
b10111111 !
b10111111 .
b10111111 /
b10111111 5
b10111 +
b10111 3
b10111 4
b0 #
b0 -
b0 0
b1 "
b1 ,
b1 1
1$
#41
0$
#42
b11100000 !
b11100000 .
b11100000 /
b11100000 5
b1011 #
b1011 -
b1011 0
b1111 "
b1111 ,
b1111 1
b11000 +
b11000 3
b11000 4
1$
#43
0$
#44
b11010111 !
b11010111 .
b11010111 /
b11010111 5
b11001 +
b11001 3
b11001 4
b1110 #
b1110 -
b1110 0
b0 "
b0 ,
b0 1
1$
#45
0$
#46
b11010000 !
b11010000 .
b11010000 /
b11010000 5
b1101 #
b1101 -
b1101 0
b111 "
b111 ,
b111 1
b11010 +
b11010 3
b11010 4
1$
#47
0$
#48
b11000111 !
b11000111 .
b11000111 /
b11000111 5
b11011 +
b11011 3
b11011 4
b0 "
b0 ,
b0 1
1$
#49
0$
#50
b11000001 !
b11000001 .
b11000001 /
b11000001 5
b1100 #
b1100 -
b1100 0
b111 "
b111 ,
b111 1
b11100 +
b11100 3
b11100 4
1$
#51
0$
#52
b10000000 !
b10000000 .
b10000000 /
b10000000 5
b11101 +
b11101 3
b11101 4
b1 "
b1 ,
b1 1
1$
#53
0$
#54
b11000000 !
b11000000 .
b11000000 /
b11000000 5
b1000 #
b1000 -
b1000 0
b0 "
b0 ,
b0 1
b11110 +
b11110 3
b11110 4
1$
#55
0$
#56
b11111111 !
b11111111 .
b11111111 /
b11111111 5
b11111 +
b11111 3
b11111 4
b1100 #
b1100 -
b1100 0
1$
#57
0$
#58
b1 !
b1 .
b1 /
b1 5
b1111 #
b1111 -
b1111 0
b1111 "
b1111 ,
b1111 1
b100000 +
b100000 3
b100000 4
1$
#59
0$
#60
b10111111 !
b10111111 .
b10111111 /
b10111111 5
b100001 +
b100001 3
b100001 4
b0 #
b0 -
b0 0
b1 "
b1 ,
b1 1
1$
#61
0$
#62
b11100000 !
b11100000 .
b11100000 /
b11100000 5
b1011 #
b1011 -
b1011 0
b1111 "
b1111 ,
b1111 1
b100010 +
b100010 3
b100010 4
1$
#63
0$
#64
b11010111 !
b11010111 .
b11010111 /
b11010111 5
b100011 +
b100011 3
b100011 4
b1110 #
b1110 -
b1110 0
b0 "
b0 ,
b0 1
1$
#65
0$
#66
b11010000 !
b11010000 .
b11010000 /
b11010000 5
b1101 #
b1101 -
b1101 0
b111 "
b111 ,
b111 1
b100100 +
b100100 3
b100100 4
1$
#67
0$
#68
b11000111 !
b11000111 .
b11000111 /
b11000111 5
b100101 +
b100101 3
b100101 4
b0 "
b0 ,
b0 1
1$
