Lab8/Ejercicio2/Ejercicio2.v
module memory (address ,data);
input [11:0] address;
output [7:0] data;


reg [7:0] mem [0:4095] ;

assign data = mem[address];

initial begin
  $readmemb("memory.txt", mem);
end

endmodule

Lab8/Ejercicio2/Ejercicio2_tb.v
module testbench();

reg [11:0] address;
wire [7:0] datos;
reg [7:0] test_memory [0:9];

memory m1(address, datos);


initial begin
#1 $display("Loading rom.");
#1 address = 8'b0;
#1 $readmemb("memory.txt", test_memory);
#5 address = 8'b1;
#5 address = 8'd2;
#5 address = 8'd3;
#5 address = 8'd4;
#5 address = 8'd5;
#5 address = 8'd6;
#5 address = 8'd7;
#5 address = 8'd8;
#5 address = 8'd9;
#500 $finish;
  end
  initial begin
         $dumpfile("Ejercicio2_tb.vcd");
         $dumpvars(0,testbench);
     end
endmodule

Lab8/Ejercicio2/Ejercicio2_tb.vcd
$date
	Fri Oct 23 21:07:02 2020
$end
$version
	Icarus Verilog
$end
$timescale
	1ps
$end
$scope module testbench $end
$var wire 8 ! datos [7:0] $end
$var reg 12 " address [11:0] $end
$scope module m1 $end
$var wire 12 # address [11:0] $end
$var wire 8 $ data [7:0] $end
$upscope $end
$upscope $end
$enddefinitions $end
#0
$dumpvars
bx $
bx #
bx "
bx !
$end
#2
b11000000 !
b11000000 $
b0 "
b0 #
#8
b11111111 !
b11111111 $
b1 "
b1 #
#13
b1 !
b1 $
b10 "
b10 #
#18
b10111111 !
b10111111 $
b11 "
b11 #
#23
b11100000 !
b11100000 $
b100 "
b100 #
#28
b11010111 !
b11010111 $
b101 "
b101 #
#33
b11010000 !
b11010000 $
b110 "
b110 #
#38
b11000111 !
b11000111 $
b111 "
b111 #
#43
b11000001 !
b11000001 $
b1000 "
b1000 #
#48
b10000000 !
b10000000 $
b1001 "
b1001 #
