Codigo/Proyecto.v
module main(input wire [1:0] tiempo, billete,
               input wire ticket, reset,sensor,clk,
               output wire factura, talanquera);
wire [3:0] ea;
wire [3:0] se;
wire [1:0] ns;
wire [1:0] as;
wire ticket_sellado;
wire ingresado;
wire timeup;
wire [2:0] vuelto;
wire [2:0] saldo;


FSM1 F1 (ea, billete, tiempo, ticket,ingresado, clk, reset,
         se, vuelto, saldo, factura, ticket_sellado, motor);

         FFD3 FF(clk, reset, se, ea);
         timer3s t0(clk, reset, motor, ingresado);


FSM2 F2 (ticket_sellado,sensor, timeup, as,clk, reset,
         ns, talanquera, contar);
        FFD1 FF1(clk, reset, ns, as);

timer7s t1(clk, reset, motor, timeup);

endmodule
//Primera maquina
module Logica_FSM1(input wire [3:0] ea, input wire [1:0] billete, tiempo, input wire ticket, ingresado,
            output wire [3:0] se, output wire [2:0] vuelto, saldo,
            output wire factura, ticket_sellado, motor);


  //cables utilizados como las compuertas intermedias
  wire n1,n2,n3, n4;
  wire n5, n6 , n7, n8, n9, n10, n11;
  wire n12, n13, n14, n15, n16, n17, n18, n19, n20;
  wire n21, n22, n23, n24, n25, n26, n27, n28, n29;
  wire n30, n31;
  wire n32, n33, n34, n35, n36, n37, n38, n39;
  wire n40, n41, n42, n43, n44, n45, n46, n47, n48, n49, n50;
  wire n51, n52, n53, n54, n55, n56, n57, n58, n59, n60;
  wire n61, n62, n63, n64, n65, n66, n67, n68, n69, n70;
  wire n71, n72, n73, n74, n75, n76, n77;

  // implementacion de las ecuaciones de la FSM

  // para SN3

assign n1 = ea[3] & ~ea[2] & ~ea[1] & ~ingresado;
assign n2 = ea[3] & ~ea[2] & ~ea[0] & ~ingresado;
assign n3 = ~ea[3] & ea[1] & ~ea[0] & billete[0] & billete[1] & ingresado;
assign n4 = ~ea[3] & ea[2] & ~ea[1] & ea[0] &  billete[0] & billete[1] & ingresado;

// para SN2

assign n5  =  ~ea[3] & ea[2] & ~ingresado;
assign n6 =  ~ea[3] & ea[2] & ~ea[1] & ~ea[0] & billete[1];
assign n7 =  ~ea[3] & ea[2] & ~ea[1] & ea[0] & billete[1];
assign n8 =  ~ea[3] & ea[2] & ea[1] & ~ea[0] & ~billete[1];
assign n9 =  ~ea[3] & ~ea[2] & ea[1] & ~billete[0] & billete[1] & ingresado;
assign n10 = ~ea[3] & ~ea[2] & ea[1] & ea[0] & billete[0] & ~billete[1] & ingresado;
assign n11 = ~ea[3] & ea[2] & ~ea[0] & ~billete[0] & ~billete[1];

// para SN1
assign n12  =  ~ea[3] & ea[1] & ~ingresado;
assign n13 =  ~ea[3] & ea[1] & ~ea[0] & ~ingresado;
assign n14 =  ~ea[3] & ~ea[2] & ea[1] & ~ea[0] & billete[1];
assign n15 =  ~ea[3] & ~ea[2] & ea[1] & ~billete[0] & ~billete[1];
assign n16 =  ~ea[3] & ea[2] & ~ea[1] & ~ea[0] & billete[0] & ingresado;
assign n17 = ~ea[3] & ea[2] & ~ea[1] & billete[0] & ~billete[1] & ingresado;
assign n18 = ~ea[3] & ea[2] & ~ea[1] & ea[0] & ~billete[0] & billete[1] & ingresado;
assign n19 = ~ea[3] & ea[2] & ea[1] & ~ea[0] & ~billete[1];
assign n20 = ~ea[3] & ~ea[2] & ~ea[1] & ~ea[0] & ticket & tiempo[0];

//para SN0
assign n21 = ~ea[3] & ea[0] & ~ingresado;
assign n22 =  ~ea[2] & ~ea[1] & ea[0] & ~ingresado;
assign n23 =  ~ea[3] & ~ea[2] & ea[1] & ea[0] & billete[0];
assign n24 = ~ea[3] & ~ea[2] & ea[1] & ea[0] & ~billete[1];
assign n25 = ~ea[3] & ea[2] & ~ea[0] & billete[1] & ingresado;
assign n26 = ~ea[3] & ea[2] & ~ea[1] & ea[0] & ~billete[0] & ~billete[1];
assign n27 = ~ea[3] & ~ea[2] & ~ea[1] & ~ea[0] & ticket& tiempo[0] & tiempo[1];
assign n28 = ~ea[3] & ~ea[2] & ~ea[1] & ~ea[0] & ticket & ~tiempo[0] & ~tiempo[1];
assign n29 = ~ea[3] & ea[1] & ~ea[0] & billete[0] & ~billete[1] & ingresado;

assign se = {n1| n2 | n3 | n4,
             n5 | n6 | n7 | n8 | n9 | n10 | n11,
             n12 | n13 | n14 | n15 | n16 | n17 | n18 | n19 | n20,
             n21 | n22 | n23 | n24 | n25 | n26 | n27 | n28 | n29};

//para los vueltos
assign n30 =  ~ea[3] & ~ea[2] & ~ea[1] & ea[0] & ~ingresado;
assign n31 =  ~ea[3] & ea[2] & ea[1] & ~ea[0] & billete[0] & billete[1]& ingresado;

assign n32 =  ea[3] & ~ea[2] & ~ea[0] & ~ingresado;
assign n33 = ~ea[3] & ea[2] & ~ea[1] & ea[0] & billete[0] & billete[1] & ingresado;
assign n34 = ~ea[3] & ~ea[2] & ea[1] & ~ea[0] & billete[0] & billete[1] & ingresado;

assign n35 = ~ea[3] & ea[2] & ea[1] & ea[0] & ~ingresado;
assign n36 = ea[3] & ~ea[2] & ea[1] & ~ea[0] & ~ingresado;
assign n37 = ~ea[3] & ~ea[2] & ea[1] & ~ea[0] & billete[0] & billete[1] & ingresado;
assign n38 = ~ea[3] & ea[2] & ~ea[1] & ~ea[0] & billete[0] & billete[1] & ingresado;
assign n39 = ~ea[3] & ea[2] & ea[1] & ~ea[0] & billete[0] & ~billete[1] & ingresado;

assign vuelto[2] = {n30 | n31};
assign vuelto[1] = {n32 | n33 | n34};
assign vuelto[0] = {n35 | n36 | n37 | n38 | n39};

//para saldo
//Saldo2
assign n40 = ~ea[3] & ~ea[2] & ea[1] & ea[0] &  ~billete[0];
assign n41 = ~ea[3] & ~ea[2] & ea[1] & ea[0] &  ~ingresado;
assign n42 = ~ea[3] & ea[2] & ~ea[1] & ~ea[0] &  ~ingresado;
assign n43 = ~ea[3] & ea[2] & ~ea[1] & ~ea[0] & ~billete[0] & ~billete[1];
assign n44 = ~ea[3] & ~ea[2] & ~ea[1] & ~ea[0] & ticket & tiempo[0] & tiempo[1];

//Saldo 1
assign n45 = ~ea[3] & ea[2] & ~ea[1] & ea[0] &  ~billete[0];
assign n46 = ~ea[3] & ea[2] & ~ea[1] & ea[0] &  ~ingresado;
assign n47 = ~ea[3] & ~ea[2] & ea[1] & ~ea[0] &  ~ingresado;
assign n48 = ~ea[3] & ~ea[2] & ea[1] & ~ea[0] &  ~billete[0] & ~billete[1];
assign n49 = ~ea[3] & ea[2] & ~ea[1] &  ~billete[0] & billete[1] & ingresado;
assign n50 = ~ea[3] & ~ea[2] & ~ea[1] & ~ea[0] & ticket & tiempo[0] & ~tiempo[1];
assign n51 = ~ea[3] & ~ea[2] & ea[1] & ea[0] & billete[0] & ~billete[1] & ingresado;
assign n52 = ~ea[3] & ea[2] & ~ea[1] & ~ea[0] & billete[0] & ~billete[1] & ingresado;

//Saldo0
assign n53 = ~ea[3] & ~ea[2] & ea[1] & ea[0] &  ~billete[1];
assign n54 = ~ea[3] & ea[2] & ~ea[1] & ea[0] &  ~billete[1];
assign n55 = ~ea[3] & ~ea[2] & ea[1] & ea[0] &  ~ingresado;
assign n56 = ~ea[3] & ea[2] & ~ea[1] & ea[0] &  ~ingresado;
assign n57 = ~ea[3] & ea[2] & ea[1] & ~ea[0] &  ~ingresado;
assign n58 = ~ea[3] & ea[2] & ea[1] & ~ea[0] &  ~billete[0] & ~billete[1];
assign n59 = ~ea[3] & ~ea[2] & ~ea[1] & ~ea[0] & ticket & tiempo[0] & tiempo [1];
assign n60 = ~ea[3] & ~ea[2] & ea[1] & ~ea[0] & ~billete[0] & billete[1] & ingresado;
assign n61 = ~ea[3] & ea[2] & ~ea[1] & ~ea[0] & ~billete[0] & billete[1] & ingresado;

assign saldo[2] = n40 | n41| n42| n43| n44;
assign saldo[1] = n45| n46| n47 | n48| n49 | n50 | n51 | n52;
assign saldo[0] = n53| n54| n55| n56| n57| n58| n59| n60| n61;

//Para factura y ticket_sellado (es lo mismo porque cuando se da factura se da el ticket sellado)

assign n62 = ~ea[2] & ~ea[1] & ea[0] & ~ingresado;
assign n63 = ea[3] & ~ea[2] & ~ea[0] & ~ingresado;
assign n64 = ~ea[3] & ea[1] & ~ea[0] & billete[0] & ingresado;
assign n65 = ~ea[3] & ea[2] & ea[1] & ea[0] & ~ingresado;
assign n66 = ~ea[3] & ea[2] & ea[1] & ~ea[0] & billete[1] & ingresado;
assign n67 = ~ea[3] & ~ea[2] & ea[1] & billete[0] & billete[1] & ingresado;
assign n68 = ~ea[3] & ea[2] & ~ea[1] & billete[0] & billete[1] & ingresado;
assign n69 = ~ea[3] & ~ea[2] & ~ea[1] & ~ea[0] & ticket & ~tiempo[0] & ~tiempo[1];

assign factura = {n62 | n63 | n64 | n65 | n66 | n67 | n68 | n69};
assign ticket_sellado = {n62 | n63 | n64 | n65 | n66 | n67 | n68 | n69};

//para motor billete
assign n70 = ~ea[3] & ~ea[2] & ea[1];
assign n71 = ~ea[3] & ea[2] & ~ea[1];
assign n72 = ~ea[3] & ~ea[0] & ticket & tiempo[0];
assign n73 = ~ea[3] & ~ea[0] & ticket & ~tiempo[1];
assign n74 = ~ea[3] & ea[1] & ~ea[0];
assign n75 = ~ea[3] & ea[0] & ~ingresado;
assign n76 = ~ea[2] & ~ea[1] & ea[0] & ~ingresado;
assign n77 = ea[3] & ~ea[2] & ~ea[0] & ~ingresado;

assign motor = {n70 | n71 | n72 | n73 | n74 | n75 | n76 | n77};

endmodule

module FSM1(input wire [3:0] ea, input wire [1:0] billete, tiempo, input wire ticket, ingresado,clk, reset,
            output wire [3:0] se, output wire [2:0] vuelto, saldo,
            output wire factura, ticket_sellado, motor);

Logica_FSM1 Logic1(ea, billete, tiempo, ticket, ingresado,
  se, vuelto, saldo, factura, ticket_sellado, motor);




endmodule


module FFD0 (input wire clk, reset,input wire D, output reg Q);
always @ (posedge clk or posedge reset) begin
if(reset)begin
Q <= 1'b0;
end
else begin
Q <= D;
end
end
endmodule

module FFD1 (input wire clk, reset, input wire [1:0]D, output reg [1:0]Q);
always@(posedge clk or posedge reset) begin
if(reset)begin
Q <= 2'b0;
end
else begin
Q <= D;
end
end
endmodule


module FFD2(input wire clk, reset, input wire [2:0] D, output reg [2:0] Q);
always@(posedge clk or posedge reset) begin
if(reset)begin
Q <= 3'b0;
end
else begin
Q <= D;
end
end
endmodule


module FFD3(input wire clk, reset, input wire [3:0] D, output reg [3:0] Q);
always@(posedge clk or posedge reset) begin
if(reset)begin
Q <= 4'b0;
end
else begin
Q <= D;
end
end
endmodule


module Logica_FSM2(input wire [1:0]as, input wire ticket_sellado, sensor, timeup,
                   output wire [1:0]ns, output wire talanquera, contar);

wire m1, m2, m3, m4, m5, m6, m7, m8;

//siguiente estado bit 1
assign m1 = as[1] & ~as[0];
assign m2 = as[0] & sensor;
assign m3 = as[1] & ~timeup;

//siguiente estado bit 0
assign m4 = ~as[1] & ~as[0] & ticket_sellado;
assign m5 = ~as[1] & as[0] & ~sensor;
assign m6 = as[1] & ~as[0] & timeup;
assign m7 = as[1] & as[0] & sensor;
assign m8 = as[1] & as[0] & ~timeup;

assign ns[1] = m1 | m2 | m3;
assign ns[0] = m4 | m5 | m6 | m7 | m8;

assign contar = as[1];
assign talanquera = {as[1] & as[0]};

endmodule

module FSM2(input wire ticket_sellado, sensor, timeup, input wire [1:0]as, input wire clk, reset,
            output wire [1:0]ns, output wire talanquera, contar);

        Logica_FSM2 Logica(as, ticket_sellado, sensor, timeup,
          ns, talanquera, contar);

endmodule

module timer3s(input wire clk, reset, motor, output reg ingresado);
reg [3:0] Q;

always @(posedge clk,posedge reset) begin Q <= (reset ? 4'b0 : Q+1);
if(Q[1] & Q[2]) begin
ingresado  <= 1'b1;
end
else begin
ingresado <= 1'b0;
end
end
endmodule

module timer7s(input clk, reset, contar, output reg timeup);
reg [3:0] Q;
always @(posedge clk,posedge reset) begin Q <= (reset ? 4'b0 : Q+1);
if(Q[1] & Q[2] & Q[3]) begin
timeup  <= 1'b1;
//reset <= 1'b1;
end
else begin
timeup <= 1'b0;
end
end

endmodule

Codigo/Proyecto_tb.v
// Proyecto testbench
module testbench();

reg ticket;
reg [1:0]billete;
reg [1:0]tiempo;
reg clk;
reg reset;
wire [3:0]se;
wire [2:0]vuelto;
wire [2:0]saldo;
wire factura;
wire ingresado;
wire ticket_sellado;
wire motor;
wire talanquera;
wire contar;
wire [3:0]ea;
reg  sensor;


main M1(tiempo, billete, ticket, reset, sensor, clk,
        factura, talanquera);

initial begin
clk = 1;
reset = 0;
#1 reset = 1;
#1 reset = 0;

sensor = 1;
#3	billete[0] =	0	;	billete[1] =	0	;	tiempo[0] =	0	;	tiempo[1] =	0	;	ticket =	0	;
#5	billete[0] =	0	;	billete[1] =	0	;	tiempo[0] =	0	;	tiempo[1] =	0	;	ticket =	1	;
#10	billete[0] =	0	;	billete[1] =	0	;	tiempo[0] =	0	;	tiempo[1] =	0	;	ticket =	1	;
#100	billete[0] =	0	;	billete[1] =	1	;	tiempo[0] =	1	;	tiempo[1] =	0	;	ticket =	1	; //se realizaron variaciones de 100
#100	billete[0] =	0	;	billete[1] =	1	;	tiempo[0] =	1	;	tiempo[1] =	0	;	ticket =	1	; //debido a que ingresado tarda en cambiar
#100	billete[0] =	0	;	billete[1] =	0	;	tiempo[0] =	1	;	tiempo[1] =	0	;	ticket =	1	; //por lo que esto facilita el cambio de estado
#100	billete[0] =	0	;	billete[1] =	0	;	tiempo[0] =	1	;	tiempo[1] =	0	;	ticket =	1	;
#100	billete[0] =	0	;	billete[1] =	0	;	tiempo[0] =	1	;	tiempo[1] =	0	;	ticket =	1	;
#100	billete[0] =	0	;	billete[1] =	0	;	tiempo[0] =	1	;	tiempo[1] =	0	;	ticket =	1	;
#100	billete[0] =	1	;	billete[1] =	0	;	tiempo[0] =	1	;	tiempo[1] =	0	;	ticket =	1	;
#100	billete[0] =	0	;	billete[1] =	0	;	tiempo[0] =	1	;	tiempo[1] =	0	;	ticket =	1	;
#100	billete[0] =	0	;	billete[1] =	1	;	tiempo[0] =	1	;	tiempo[1] =	0	;	ticket =	1	;
#100	billete[0] =	0	;	billete[1] =	1	;	tiempo[0] =	1	;	tiempo[1] =	0	;	ticket =	1	;
#100	billete[0] =	0	;	billete[1] =	0	;	tiempo[0] =	1	;	tiempo[1] =	0	;	ticket =	1	;
#100	billete[0] =	1	;	billete[1] =	1	;	tiempo[0] =	1	;	tiempo[1] =	0	;	ticket =	1	;
#100	billete[0] =	0	;	billete[1] =	0	;	tiempo[0] =	1	;	tiempo[1] =	0	;	ticket =	1	;
#100	billete[0] =	0	;	billete[1] =	0	;	tiempo[0] =	1	;	tiempo[1] =	0	;	ticket =	1	;
#100	billete[0] =	0	;	billete[1] =	0	;	tiempo[0] =	1	;	tiempo[1] =	0	;	ticket =	1	;
#100	billete[0] =	1	;	billete[1] =	1	;	tiempo[0] =	1	;	tiempo[1] =	1	;	ticket =	1	;
#100	billete[0] =	1	;	billete[1] =	1	;	tiempo[0] =	1	;	tiempo[1] =	1	;	ticket =	1	;
#100	billete[0] =	0	;	billete[1] =	0	;	tiempo[0] =	1	;	tiempo[1] =	1	;	ticket =	1	;
#100	billete[0] =	0	;	billete[1] =	1	;	tiempo[0] =	1	;	tiempo[1] =	1	;	ticket =	1	;
#100	billete[0] =	0	;	billete[1] =	1	;	tiempo[0] =	1	;	tiempo[1] =	1	;	ticket =	1	; sensor =0;
#100	billete[0] =	0	;	billete[1] =	1	;	tiempo[0] =	1	;	tiempo[1] =	1	;	ticket =	1	;
#100	billete[0] =	0	;	billete[1] =	1	;	tiempo[0] =	1	;	tiempo[1] =	1	;	ticket =	1	;
#100	billete[0] =	0	;	billete[1] =	1	;	tiempo[0] =	1	;	tiempo[1] =	1	;	ticket =	1	;
#100	billete[0] =	0	;	billete[1] =	0	;	tiempo[0] =	1	;	tiempo[1] =	1	;	ticket =	1	;
#100	billete[0] =	0	;	billete[1] =	1	;	tiempo[0] =	1	;	tiempo[1] =	1	;	ticket =	1	;
#100	billete[0] =	0	;	billete[1] =	1	;	tiempo[0] =	1	;	tiempo[1] =	1	;	ticket =	1	;
#100	billete[0] =	1	;	billete[1] =	0	;	tiempo[0] =	1	;	tiempo[1] =	1	;	ticket =	1	; sensor = 1;
#100	billete[0] =	0	;	billete[1] =	1	;	tiempo[0] =	1	;	tiempo[1] =	1	;	ticket =	1	;
#100	billete[0] =	0	;	billete[1] =	0	;	tiempo[0] =	1	;	tiempo[1] =	1	;	ticket =	1	;
#100	billete[0] =	0	;	billete[1] =	0	;	tiempo[0] =	1	;	tiempo[1] =	1	;	ticket =	1	;
#100	billete[0] =	1	;	billete[1] =	0	;	tiempo[0] =	1	;	tiempo[1] =	1	;	ticket =	1	;
#100	billete[0] =	1	;	billete[1] =	0	;	tiempo[0] =	1	;	tiempo[1] =	1	;	ticket =	1	;
#100	billete[0] =	1	;	billete[1] =	1	;	tiempo[0] =	1	;	tiempo[1] =	1	;	ticket =	1	;
#100	billete[0] =	0	;	billete[1] =	0	;	tiempo[0] =	1	;	tiempo[1] =	1	;	ticket =	1	;
#100	billete[0] =	1	;	billete[1] =	0	;	tiempo[0] =	1	;	tiempo[1] =	1	;	ticket =	1	;
#100	billete[0] =	1	;	billete[1] =	0	;	tiempo[0] =	1	;	tiempo[1] =	1	;	ticket =	1	;
#100	billete[0] =	1	;	billete[1] =	0	;	tiempo[0] =	1	;	tiempo[1] =	1	;	ticket =	1	;
#100	billete[0] =	0	;	billete[1] =	0	;	tiempo[0] =	1	;	tiempo[1] =	1	;	ticket =	1	;
#100	billete[0] =	0	;	billete[1] =	1	;	tiempo[0] =	1	;	tiempo[1] =	1	;	ticket =	1	;
#100	billete[0] =	1	;	billete[1] =	1	;	tiempo[0] =	1	;	tiempo[1] =	1	;	ticket =	1	;
#100	billete[0] =	0	;	billete[1] =	0	;	tiempo[0] =	1	;	tiempo[1] =	1	;	ticket =	1	;
#100	billete[0] =	0	;	billete[1] =	0	;	tiempo[0] =	1	;	tiempo[1] =	1	;	ticket =	1	;
#100	billete[0] =	0	;	billete[1] =	0	;	tiempo[0] =	1	;	tiempo[1] =	1	;	ticket =	1	;
#100	billete[0] =	0	;	billete[1] =	0	;	tiempo[0] =	1	;	tiempo[1] =	1	;	ticket =	1	;
#100	billete[0] =	0	;	billete[1] =	0	;	tiempo[0] =	1	;	tiempo[1] =	1	;	ticket =	1	;
#100	billete[0] =	0	;	billete[1] =	0	;	tiempo[0] =	1	;	tiempo[1] =	1	;	ticket =	1	;




#500 $finish;
end

always
  #5 clk = !clk;




initial begin
       $dumpfile("Proyecto_tb.vcd");
       $dumpvars(0,testbench);
   end
endmodule

Codigo/Proyecto_tb.vcd
$date
	Sun Oct 11 18:59:43 2020
$end
$version
	Icarus Verilog
$end
$timescale
	1ps
$end
$scope module testbench $end
$var wire 1 ! talanquera $end
$var wire 1 " factura $end
$var reg 2 # billete [1:0] $end
$var reg 1 $ clk $end
$var reg 1 % reset $end
$var reg 1 & sensor $end
$var reg 1 ' ticket $end
$var reg 2 ( tiempo [1:0] $end
$scope module M1 $end
$var wire 2 ) billete [1:0] $end
$var wire 1 $ clk $end
$var wire 1 % reset $end
$var wire 1 & sensor $end
$var wire 1 ' ticket $end
$var wire 2 * tiempo [1:0] $end
$var wire 3 + vuelto [2:0] $end
$var wire 1 , timeup $end
$var wire 1 - ticket_sellado $end
$var wire 1 ! talanquera $end
$var wire 4 . se [3:0] $end
$var wire 3 / saldo [2:0] $end
$var wire 2 0 ns [1:0] $end
$var wire 1 1 motor $end
$var wire 1 2 ingresado $end
$var wire 1 " factura $end
$var wire 4 3 ea [3:0] $end
$var wire 1 4 contar $end
$var wire 2 5 as [1:0] $end
$scope module F1 $end
$var wire 2 6 billete [1:0] $end
$var wire 1 $ clk $end
$var wire 1 % reset $end
$var wire 1 ' ticket $end
$var wire 2 7 tiempo [1:0] $end
$var wire 3 8 vuelto [2:0] $end
$var wire 1 - ticket_sellado $end
$var wire 4 9 se [3:0] $end
$var wire 3 : saldo [2:0] $end
$var wire 1 1 motor $end
$var wire 1 2 ingresado $end
$var wire 1 " factura $end
$var wire 4 ; ea [3:0] $end
$scope module Logic1 $end
$var wire 2 < billete [1:0] $end
$var wire 1 = n1 $end
$var wire 1 > n10 $end
$var wire 1 ? n11 $end
$var wire 1 @ n12 $end
$var wire 1 A n13 $end
$var wire 1 B n14 $end
$var wire 1 C n15 $end
$var wire 1 D n16 $end
$var wire 1 E n17 $end
$var wire 1 F n18 $end
$var wire 1 G n19 $end
$var wire 1 H n2 $end
$var wire 1 I n20 $end
$var wire 1 J n21 $end
$var wire 1 K n22 $end
$var wire 1 L n23 $end
$var wire 1 M n24 $end
$var wire 1 N n25 $end
$var wire 1 O n26 $end
$var wire 1 P n27 $end
$var wire 1 Q n28 $end
$var wire 1 R n29 $end
$var wire 1 S n3 $end
$var wire 1 T n30 $end
$var wire 1 U n31 $end
$var wire 1 V n32 $end
$var wire 1 W n33 $end
$var wire 1 X n34 $end
$var wire 1 Y n35 $end
$var wire 1 Z n36 $end
$var wire 1 [ n37 $end
$var wire 1 \ n38 $end
$var wire 1 ] n39 $end
$var wire 1 ^ n4 $end
$var wire 1 _ n40 $end
$var wire 1 ` n41 $end
$var wire 1 a n42 $end
$var wire 1 b n43 $end
$var wire 1 c n44 $end
$var wire 1 d n45 $end
$var wire 1 e n46 $end
$var wire 1 f n47 $end
$var wire 1 g n48 $end
$var wire 1 h n49 $end
$var wire 1 i n5 $end
$var wire 1 j n50 $end
$var wire 1 k n51 $end
$var wire 1 l n52 $end
$var wire 1 m n53 $end
$var wire 1 n n54 $end
$var wire 1 o n55 $end
$var wire 1 p n56 $end
$var wire 1 q n57 $end
$var wire 1 r n58 $end
$var wire 1 s n59 $end
$var wire 1 t n6 $end
$var wire 1 u n60 $end
$var wire 1 v n61 $end
$var wire 1 w n62 $end
$var wire 1 x n63 $end
$var wire 1 y n64 $end
$var wire 1 z n65 $end
$var wire 1 { n66 $end
$var wire 1 | n67 $end
$var wire 1 } n68 $end
$var wire 1 ~ n69 $end
$var wire 1 !" n7 $end
$var wire 1 "" n70 $end
$var wire 1 #" n71 $end
$var wire 1 $" n72 $end
$var wire 1 %" n73 $end
$var wire 1 &" n74 $end
$var wire 1 '" n75 $end
$var wire 1 (" n76 $end
$var wire 1 )" n77 $end
$var wire 1 *" n8 $end
$var wire 1 +" n9 $end
$var wire 1 ' ticket $end
$var wire 2 ," tiempo [1:0] $end
$var wire 3 -" vuelto [2:0] $end
$var wire 1 - ticket_sellado $end
$var wire 4 ." se [3:0] $end
$var wire 3 /" saldo [2:0] $end
$var wire 1 1 motor $end
$var wire 1 2 ingresado $end
$var wire 1 " factura $end
$var wire 4 0" ea [3:0] $end
$upscope $end
$upscope $end
$scope module F2 $end
$var wire 1 $ clk $end
$var wire 1 % reset $end
$var wire 1 & sensor $end
$var wire 1 - ticket_sellado $end
$var wire 1 , timeup $end
$var wire 1 ! talanquera $end
$var wire 2 1" ns [1:0] $end
$var wire 1 4 contar $end
$var wire 2 2" as [1:0] $end
$scope module Logica $end
$var wire 1 3" m1 $end
$var wire 1 4" m2 $end
$var wire 1 5" m3 $end
$var wire 1 6" m4 $end
$var wire 1 7" m5 $end
$var wire 1 8" m6 $end
$var wire 1 9" m7 $end
$var wire 1 :" m8 $end
$var wire 1 & sensor $end
$var wire 1 - ticket_sellado $end
$var wire 1 , timeup $end
$var wire 1 ! talanquera $end
$var wire 2 ;" ns [1:0] $end
$var wire 1 4 contar $end
$var wire 2 <" as [1:0] $end
$upscope $end
$upscope $end
$scope module FF $end
$var wire 4 =" D [3:0] $end
$var wire 1 $ clk $end
$var wire 1 % reset $end
$var reg 4 >" Q [3:0] $end
$upscope $end
$scope module FF1 $end
$var wire 2 ?" D [1:0] $end
$var wire 1 $ clk $end
$var wire 1 % reset $end
$var reg 2 @" Q [1:0] $end
$upscope $end
$scope module t0 $end
$var wire 1 $ clk $end
$var wire 1 1 motor $end
$var wire 1 % reset $end
$var reg 4 A" Q [3:0] $end
$var reg 1 2 ingresado $end
$upscope $end
$scope module t1 $end
$var wire 1 $ clk $end
$var wire 1 1 contar $end
$var wire 1 % reset $end
$var reg 4 B" Q [3:0] $end
$var reg 1 , timeup $end
$upscope $end
$upscope $end
$upscope $end
$enddefinitions $end
#0
$dumpvars
bx B"
bx A"
bx @"
bx ?"
bx >"
bx ="
bx <"
bx ;"
x:"
x9"
08"
x7"
x6"
x5"
x4"
x3"
bx 2"
bx 1"
bx 0"
bx /"
bx ."
bx -"
bx ,"
0+"
x*"
x)"
x("
x'"
x&"
x%"
x$"
x#"
x""
x!"
x~
0}
0|
0{
xz
0y
xx
xw
0v
0u
xt
xs
xr
xq
xp
xo
xn
xm
0l
0k
xj
xi
0h
xg
xf
xe
xd
xc
xb
xa
x`
x_
0^
0]
0\
0[
xZ
xY
0X
0W
xV
0U
xT
0S
0R
xQ
xP
xO
0N
xM
xL
xK
xJ
xI
xH
xG
0F
0E
0D
xC
xB
xA
x@
x?
0>
x=
bx <
bx ;
bx :
bx 9
bx 8
bx 7
bx 6
bx 5
x4
bx 3
02
x1
bx 0
bx /
bx .
x-
0,
bx +
bx *
bx )
bx (
x'
x&
0%
1$
bx #
x"
x!
$end
#1
b0xx .
b0xx 9
b0xx ."
b0xx ="
0r
0g
0b
0?
0)"
0x
0q
0f
0a
0Z
0V
b0 +
b0 8
b0 -"
0O
0G
0C
0B
0A
0*"
0t
0H
0=
0:"
09"
07"
b0x 0
b0x 1"
b0x ;"
b0x ?"
0("
0'"
0&"
0#"
0z
0w
0p
0o
0n
0m
0e
0d
0`
0_
0Y
0T
0M
0L
0K
0J
0@
0!"
0i
0!
05"
04"
03"
0""
04
b0 B"
b0 5
b0 2"
b0 <"
b0 @"
b0 A"
b0 3
b0 ;
b0 0"
b0 >"
1%
#2
1&
0%
#5
b0 0
b0 1"
b0 ;"
b0 ?"
01
06"
0"
0-
0Q
b0 /
b0 :
b0 /"
0~
b0 .
b0 9
b0 ."
b0 ="
0j
0%"
0P
0c
0s
0I
0$"
0'
b0 (
b0 *
b0 7
b0 ,"
b0 #
b0 )
b0 6
b0 <
0$
#10
b1 A"
b1 B"
b1 0
b1 1"
b1 ;"
b1 ?"
11
b1 .
b1 9
b1 ."
b1 ="
16"
1"
1-
1Q
1~
1%"
1'
1$
#15
0$
#20
b1 .
b1 9
b1 ."
b1 ="
1"
1-
0~
0Q
0%"
06"
b10 0
b10 1"
b10 ;"
b10 ?"
b100 +
b100 8
b100 -"
1("
1'"
1w
1T
1K
1J
14"
b10 B"
b1 5
b1 2"
b1 <"
b1 @"
b10 A"
b1 3
b1 ;
b1 0"
b1 >"
1$
#25
0$
#30
13"
15"
04"
14
b11 A"
b10 5
b10 2"
b10 <"
b10 @"
b11 B"
1$
#35
0$
#40
b100 B"
b100 A"
1$
#45
0$
#50
b101 A"
b101 B"
1$
#55
0$
#60
b110 B"
b110 A"
1$
#65
0$
#70
b0 .
b0 9
b0 ."
b0 ="
0"
0-
01
b0 +
b0 8
b0 -"
0("
0'"
0w
0T
0K
0J
12
b111 A"
b111 B"
1$
#75
0$
#80
11
b1 .
b1 9
b1 ."
b1 ="
1"
1-
1~
1Q
1%"
b1000 B"
b1000 A"
b0 3
b0 ;
b0 0"
b0 >"
1$
#85
0$
#90
b1 .
b1 9
b1 ."
b1 ="
1"
1-
0~
0Q
0%"
b100 +
b100 8
b100 -"
1("
1'"
1w
1T
1K
1J
b1 3
b1 ;
b1 0"
b1 >"
02
b1001 A"
b1001 B"
1$
#95
0$
#100
b1010 B"
b1010 A"
1$
#105
0$
#110
b1011 A"
b1011 B"
1$
#115
0$
#120
b1100 B"
b1100 A"
1$
b1 (
b1 *
b1 7
b1 ,"
b10 #
b10 )
b10 6
b10 <
#125
0$
#130
b1101 A"
b1101 B"
1$
#135
0$
#140
b1110 B"
b1110 A"
1$
#145
0$
#150
b0 .
b0 9
b0 ."
b0 ="
0"
0-
01
b11 0
b11 1"
b11 ;"
b11 ?"
b0 +
b0 8
b0 -"
0("
0'"
0w
0T
0K
0J
05"
18"
12
b1111 A"
1,
b1111 B"
1$
#155
0$
#160
11
b10 /
b10 :
b10 /"
1j
b10 .
b10 9
b10 ."
b10 ="
1%"
1$"
1I
08"
19"
03"
1!
14"
b0 B"
b11 5
b11 2"
b11 <"
b11 @"
b0 A"
b0 3
b0 ;
b0 0"
b0 >"
1$
#165
0$
#170
0j
b10 .
b10 9
b10 ."
b10 ="
0I
1f
1B
1A
1&"
1@
1""
1:"
15"
b10 3
b10 ;
b10 0"
b10 >"
02
b1 A"
0,
b1 B"
1$
#175
0$
#180
b10 B"
b10 A"
1$
#185
0$
#190
b11 A"
b11 B"
1$
#195
0$
#200
b100 B"
b100 A"
1$
#205
0$
#210
b101 A"
b101 B"
1$
#215
0$
#220
b110 B"
b110 A"
1$
#225
0$
#230
b110 .
b110 9
b110 ."
b110 ="
b1 /
b1 :
b1 /"
0f
0A
0@
1u
1+"
12
b111 A"
b111 B"
1$
#235
0$
#240
1"
1-
b0 /
b0 :
b0 /"
b1 .
b1 9
b1 ."
b1 ="
0u
0+"
1{
0B
1N
0""
b1000 B"
b1000 A"
b110 3
b110 ;
b110 0"
b110 >"
1$
#245
0$
#250
b0 /
b0 :
b0 /"
b100 +
b100 8
b100 -"
b1 .
b1 9
b1 ."
b1 ="
1("
0%"
0$"
1w
1T
1K
1"
1-
1'"
0&"
1J
0q
0A
0@
0i
0{
0N
b1 3
b1 ;
b1 0"
b1 >"
02
b1001 A"
b1001 B"
1$
#255
0$
#260
b1010 B"
b1010 A"
1$
#265
0$
#270
b1011 A"
b1011 B"
1$
#275
0$
#280
b1100 B"
b1100 A"
1$
