Lab9/Ejercicio1/Ejercicio1.v
module FFD(input enable, reset, clk, D, output  reg Q);

always @ (posedge clk, posedge reset)
begin
  begin
  if (reset)
    Q <= 0;
  else if (~enable)
    Q <=Q;
  else
  Q <= D;
  end
end
  endmodule


module FFD2 (input enable, reset, clk, input [1:0] D2, output wire [1:0] Q2 );

  FFD FFDA(enable, reset, clk, D2[0], Q2[0]);
  FFD FFDB(enable, reset, clk, D2[1], Q2[1]);

    endmodule

module FFD4 (input enable, reset, clk, input [3:0] D3, output wire [3:0] Q3);
  FFD2 FFD2A(enable, reset, clk, D3[1:0], Q3[1:0]);
  FFD2 FFD2B(enable, reset, clk, D3[3:2], Q3[3:2]);

  endmodule

Lab9/Ejercicio1/Ejercicio1_tb.v
module testbench();

reg enable;
reg reset;
reg clk;
reg D;
wire Q;
reg [1:0] D2;
wire [1:0] Q2;
reg [3:0] D3;
wire [3:0] Q3;



FFD F1(enable, reset, clk, D, Q);
FFD2 F2(enable, reset, clk, D2, Q2);
FFD4 F3(enable, reset, clk, D3, Q3);
integer i;

initial begin
clk = 1;
reset = 0;
#2 reset = 1;
#2 reset = 0;
#2 enable = 0;
#2 enable = 1;
#2 D = 1'b0; D2 = 2'b0; D3 = 4'd0;
#2 D = 1'b1; D2 = 2'd2; D3 =4'd5;


reset = 1;
#1 reset = 0;


#50 enable = 0;
#2 D = 1'b0; D2 = 2'd4; D3 =4'd12;


  #50 $finish;
end

always
#1 clk = !clk;




initial begin
       $dumpfile("Ejercicio1_tb.vcd");
       $dumpvars(0,testbench);
   end
endmodule

Lab9/Ejercicio1/Ejercicio1_tb.vcd
$date
	Sat Oct 31 10:32:51 2020
$end
$version
	Icarus Verilog
$end
$timescale
	1ps
$end
$scope module testbench $end
$var wire 4 ! Q3 [3:0] $end
$var wire 2 " Q2 [1:0] $end
$var wire 1 # Q $end
$var reg 1 $ D $end
$var reg 2 % D2 [1:0] $end
$var reg 4 & D3 [3:0] $end
$var reg 1 ' clk $end
$var reg 1 ( enable $end
$var reg 1 ) reset $end
$scope module F1 $end
$var wire 1 $ D $end
$var wire 1 ' clk $end
$var wire 1 ( enable $end
$var wire 1 ) reset $end
$var reg 1 # Q $end
$upscope $end
$scope module F2 $end
$var wire 2 * D2 [1:0] $end
$var wire 1 ' clk $end
$var wire 1 ( enable $end
$var wire 1 ) reset $end
$var wire 2 + Q2 [1:0] $end
$scope module FFDA $end
$var wire 1 , D $end
$var wire 1 ' clk $end
$var wire 1 ( enable $end
$var wire 1 ) reset $end
$var reg 1 - Q $end
$upscope $end
$scope module FFDB $end
$var wire 1 . D $end
$var wire 1 ' clk $end
$var wire 1 ( enable $end
$var wire 1 ) reset $end
$var reg 1 / Q $end
$upscope $end
$upscope $end
$scope module F3 $end
$var wire 4 0 D3 [3:0] $end
$var wire 1 ' clk $end
$var wire 1 ( enable $end
$var wire 1 ) reset $end
$var wire 4 1 Q3 [3:0] $end
$scope module FFD2A $end
$var wire 2 2 D2 [1:0] $end
$var wire 1 ' clk $end
$var wire 1 ( enable $end
$var wire 1 ) reset $end
$var wire 2 3 Q2 [1:0] $end
$scope module FFDA $end
$var wire 1 4 D $end
$var wire 1 ' clk $end
$var wire 1 ( enable $end
$var wire 1 ) reset $end
$var reg 1 5 Q $end
$upscope $end
$scope module FFDB $end
$var wire 1 6 D $end
$var wire 1 ' clk $end
$var wire 1 ( enable $end
$var wire 1 ) reset $end
$var reg 1 7 Q $end
$upscope $end
$upscope $end
$scope module FFD2B $end
$var wire 2 8 D2 [1:0] $end
$var wire 1 ' clk $end
$var wire 1 ( enable $end
$var wire 1 ) reset $end
$var wire 2 9 Q2 [1:0] $end
$scope module FFDA $end
$var wire 1 : D $end
$var wire 1 ' clk $end
$var wire 1 ( enable $end
$var wire 1 ) reset $end
$var reg 1 ; Q $end
$upscope $end
$scope module FFDB $end
$var wire 1 < D $end
$var wire 1 ' clk $end
$var wire 1 ( enable $end
$var wire 1 ) reset $end
$var reg 1 = Q $end
$upscope $end
$upscope $end
$upscope $end
$upscope $end
$enddefinitions $end
#0
$dumpvars
x=
x<
x;
x:
bx 9
bx 8
x7
x6
x5
x4
bx 3
bx 2
bx 1
bx 0
x/
x.
x-
x,
bx +
bx *
0)
x(
1'
bx &
bx %
x$
x#
bx "
bx !
$end
#1
0'
#2
0=
b0 9
0;
07
b0 !
b0 1
b0 3
05
0/
b0 "
b0 +
0-
0#
1'
1)
#3
0'
#4
x#
x-
bx "
bx +
x/
x5
bx 3
x7
x;
bx !
bx 1
bx 9
x=
1'
0)
#5
0'
#6
1'
0(
#7
0'
#8
1'
1(
#9
0'
#10
0/
b0 "
b0 +
0-
0#
04
06
0:
0<
b0 2
b0 8
0,
0.
1'
b0 &
b0 0
b0 %
b0 *
0$
#11
0'
#12
05
b0 3
07
0;
b0 !
b0 1
b0 9
0=
14
1:
b1 2
b1 8
1.
1'
1)
b101 &
b101 0
b10 %
b10 *
1$
#13
0'
0)
#14
b1 9
1;
b101 !
b101 1
b1 3
15
b10 "
b10 +
1/
1#
1'
