Lab9/Ejercicio3/Ejercicio3.v
module FFJK(input enable, reset, clk, J, K, output wire Q);

wire D;

assign D = (J & ~Q) | (~K & Q);

FFD F1(enable, reset, clk, D, Q);


endmodule






module FFD(input enable, reset, clk, D, output  reg Q);

always @ (posedge clk, posedge reset)
begin
  begin
  if (reset)
    Q <= 0;
  else if (~enable)
    Q <=Q;
  else
  Q <= D;
  end
end
  endmodule

Lab9/Ejercicio3/Ejercicio3_tb.v
module testbench();

wire Q;
reg enable;
reg reset;
reg clk;
reg J;
reg K;



FFJK F1(enable, reset, clk, J, K, Q);


initial begin
clk = 1;
reset = 0;
#2 reset = 1; J = 1; K = 0;
#2 reset = 0;
#2 enable = 0;
#2 enable = 1;


#10 J = 0; K = 1;
#10 J = 1; K = 1;
#10 J = 0; K = 0;

#50 enable = 0;
  #10 $finish;
end

always
#1 clk = !clk;




initial begin
       $dumpfile("Ejercicio3_tb.vcd");
       $dumpvars(0,testbench);
   end
endmodule

Lab9/Ejercicio3/Ejercicio3_tb.vcd
$date
	Fri Oct 30 16:25:14 2020
$end
$version
	Icarus Verilog
$end
$timescale
	1ps
$end
$scope module testbench $end
$var wire 1 ! Q $end
$var reg 1 " J $end
$var reg 1 # K $end
$var reg 1 $ clk $end
$var reg 1 % enable $end
$var reg 1 & reset $end
$scope module F1 $end
$var wire 1 ' D $end
$var wire 1 " J $end
$var wire 1 # K $end
$var wire 1 $ clk $end
$var wire 1 % enable $end
$var wire 1 & reset $end
$var wire 1 ! Q $end
$scope module F1 $end
$var wire 1 ' D $end
$var wire 1 $ clk $end
$var wire 1 % enable $end
$var wire 1 & reset $end
$var reg 1 ! Q $end
$upscope $end
$upscope $end
$upscope $end
$enddefinitions $end
#0
$dumpvars
x'
0&
x%
1$
x#
x"
x!
$end
#1
0$
#2
1'
0!
1$
0#
1"
1&
#3
0$
#4
1!
1$
0&
#5
0$
#6
1$
0%
#7
0$
#8
1$
1%
#9
0$
#10
1$
#11
0$
#12
1$
#13
0$
#14
1$
#15
0$
#16
1$
#17
0$
#18
0'
1$
1#
0"
#19
0$
#20
0!
1$
#21
0$
#22
1$
#23
0$
#24
1$
#25
0$
#26
1$
#27
0$
#28
1'
1$
1"
#29
0$
#30
0'
1!
1$
#31
0$
#32
1'
0!
1$
#33
0$
#34
0'
1!
1$
#35
0$
#36
1'
0!
1$
#37
0$
#38
1!
1'
1$
0#
0"
