Lab9/Ejercicio2/Ejercicio2.v
module FFT (input wire enable, reset, clk, output wire Q);

FFD F1(enable, reset, clk, ~Q, Q);

endmodule

module FFD(input enable, reset, clk, D, output  reg Q);

always @ (posedge clk, posedge reset)
begin
  begin
  if (reset)
    Q <= 0;
  else if (~enable)
    Q <=Q;
  else
  Q <= D;
  end
end
  endmodule

Lab9/Ejercicio2/Ejercicio2_tb.v
module testbench();

reg enable;
reg reset;
reg clk;
wire Q;



FFT T1(enable, reset, clk, Q);


initial begin
#2 enable = 0;
#2 enable = 1;
clk = 1;
reset = 0;
#2 reset = 1;
#2 reset = 0;



reset = 1;
#1 reset = 0;


#50 enable = 0;
  #500 $finish;
end

always
#1 clk = !clk;




initial begin
       $dumpfile("Ejercicio2_tb.vcd");
       $dumpvars(0,testbench);
   end
endmodule

Lab9/Ejercicio2/Ejercicio2_tb.vcd
$date
	Fri Oct 30 12:49:02 2020
$end
$version
	Icarus Verilog
$end
$timescale
	1ps
$end
$scope module testbench $end
$var wire 1 ! Q $end
$var reg 1 " clk $end
$var reg 1 # enable $end
$var reg 1 $ reset $end
$scope module T1 $end
$var wire 1 " clk $end
$var wire 1 # enable $end
$var wire 1 $ reset $end
$var wire 1 ! Q $end
$scope module F1 $end
$var wire 1 % D $end
$var wire 1 " clk $end
$var wire 1 # enable $end
$var wire 1 $ reset $end
$var reg 1 ! Q $end
$upscope $end
$upscope $end
$upscope $end
$enddefinitions $end
#0
$dumpvars
x%
x$
x#
x"
x!
$end
#2
0#
#4
0$
0"
1#
#5
1"
#6
1%
0!
0"
1$
#7
1"
#8
0"
1$
#9
0%
1!
1"
0$
#10
0"
#11
1%
0!
1"
#12
0"
#13
0%
1!
1"
#14
0"
#15
1%
0!
1"
#16
0"
#17
0%
1!
1"
#18
0"
#19
1%
0!
1"
#20
0"
#21
0%
1!
1"
#22
0"
#23
1%
0!
1"
#24
0"
#25
0%
1!
1"
#26
0"
#27
1%
0!
1"
#28
0"
#29
0%
1!
1"
#30
0"
#31
1%
0!
1"
#32
0"
#33
0%
1!
1"
#34
0"
#35
1%
0!
1"
#36
0"
#37
0%
1!
1"
#38
0"
#39
1%
0!
1"
#40
0"
#41
0%
1!
1"
#42
0"
#43
1%
0!
1"
#44
0"
#45
0%
1!
1"
#46
0"
#47
1%
0!
1"
#48
0"
#49
0%
1!
1"
#50
0"
#51
1%
0!
1"
#52
0"
#53
0%
1!
1"
#54
0"
#55
1%
0!
1"
#56
0"
#57
0%
1!
1"
#58
0"
#59
1"
0#
