Lab9/Ejercicio2/Ejercicio2.v
module FFT (input wire enable, reset, clk, output wire Q);

FFD F1(enable, reset, clk, ~Q, Q);

endmodule

module FFD(input enable, reset, clk, D, output  reg Q);

always @ (posedge clk, posedge reset)
begin
  begin
  if (reset)
    Q <= 0;
  else if (~enable)
    Q <=Q;
  else
  Q <= D;
  end
end
  endmodule

Lab9/Ejercicio2/Ejercicio2_tb.v
module testbench();

reg enable;
reg reset;
reg clk;
wire Q;



FFT T1(enable, reset, clk, Q);


initial begin
#2 enable = 0;
#2 enable = 1;
clk = 1;
reset = 0;
#2 reset = 1;
#2 reset = 0;



reset = 1;
#1 reset = 0;


#50 enable = 0;
  #500 $finish;
end

always
#1 clk = !clk;




initial begin
       $dumpfile("Ejercicio2_tb.vcd");
       $dumpvars(0,testbench);
   end
endmodule

Lab9/Ejercicio2/Ejercicio1_tb.vcd
$date
	Fri Oct 30 12:44:56 2020
$end
$version
	Icarus Verilog
$end
$timescale
	1ps
$end
$scope module testbench $end
$var wire 1 ! Q $end
$var reg 1 " clk $end
$var reg 1 # enable $end
$var reg 1 $ reset $end
$scope module T1 $end
$var wire 1 " clk $end
$var wire 1 # enable $end
$var wire 1 $ reset $end
$var wire 1 ! Q $end
$scope module F1 $end
$var wire 1 % D $end
$var wire 1 " clk $end
$var wire 1 # enable $end
$var wire 1 $ reset $end
$var reg 1 ! Q $end
$upscope $end
$upscope $end
$upscope $end
$enddefinitions $end
#0
$dumpvars
x%
0$
x#
1"
x!
$end
#1
0"
#2
1%
0!
1"
1$
#3
0"
#4
0%
1!
1"
0$
#5
0"
#6
1"
0#
#7
0"
#8
1%
0!
1"
1$
1#
#9
0"
0$
#10
0%
1!
1"
#11
0"
#12
1%
0!
1"
#13
0"
#14
0%
1!
1"
#15
0"
#16
1%
0!
1"
#17
0"
#18
0%
1!
1"
#19
0"
#20
1%
0!
1"
#21
0"
#22
0%
1!
1"
#23
0"
#24
1%
0!
1"
#25
0"
#26
0%
1!
1"
#27
0"
#28
1%
0!
1"
#29
0"
#30
0%
1!
1"
#31
0"
#32
1%
0!
1"
#33
0"
#34
0%
1!
1"
#35
0"
#36
1%
0!
1"
#37
0"
#38
0%
1!
1"
#39
0"
#40
1%
0!
1"
#41
0"
#42
0%
1!
1"
#43
0"
#44
1%
0!
1"
#45
0"
#46
0%
1!
1"
#47
0"
#48
1%
0!
1"
#49
0"
#50
0%
1!
1"
#51
0"
#52
1%
0!
1"
#53
0"
#54
0%
1!
1"
#55
0"
#56
1%
0!
1"
#57
0"
#58
0%
1!
1"
#59
0"
0#
