Lab9/Ejercicio5/Ejercicio5.v
module memory (input [6:0]address ,output reg [12:0] data);


always @ (*)
begin
case (address)

7'bxxxxxx0: data = 13'b1000000001000;
7'b00001x1: data = 13'b0100000001000;
7'b00000x1: data = 13'b1000000001000;
7'b00011x1: data = 13'b1000000001000;
7'b00010x1: data = 13'b0100000001000;
7'b0010xx1: data = 13'b0001001000010;
7'b0011xx1: data = 13'b1001001100000;
7'b0100xx1: data = 13'b0011010000010;
7'b0101xx1: data = 13'b0011010000100;
7'b0110xx1: data = 13'b1011010100000;
7'b0111xx1: data = 13'b1000000111000;
7'b1000x11: data = 13'b0100000001000;
7'b1000x01: data = 13'b1000000001000;
7'b1001x11: data = 13'b1000000001000;
7'b1001x01: data = 13'b0100000001000;
7'b1010xx1: data = 13'b0011011000010;
7'b1011xx1: data = 13'b1011011100000;
7'b1100xx1: data = 13'b0100000001000;
7'b1101xx1: data = 13'b0000000001001;
7'b1110xx1: data = 13'b0011100000010;
7'b1111xx1: data = 13'b1011100100000;

default data = 0;

endcase
end
endmodule

Lab9/Ejercicio5/Ejercicio5_tb.v
module testbench();

wire [12:0]data;
reg [6:0]address;

memory M1(address, data);

initial begin
address = 7'bxxxxxx0;
#10 address = 7'b00001x1;
#10 address= 7'b00000x1;
#10 address= 7'b00000x1;
#10 address=7'b00011x1;
#10 address=7'b00010x1;
#10 address=7'b0010xx1;
#10 address=7'b0011xx1;
#10 address=7'b0100xx1;
#10 address=7'b0101xx1;
#10 address=7'b0110xx1;
#10 address=7'b0111xx1;
#10 address=7'b1000x11;
#10 address=7'b1000x01;
#10 address=7'b1001x11;
#10 address=7'b1001x01;
#10 address=7'b1010xx1;
#10 address=7'b1011xx1;
#10 address=7'b1100xx1;
#10 address=7'b1101xx1;
#10 address=7'b1110xx1;
#10 address=7'b1111xx1;

//probando otras que no son de la lista
#10 address = 7'b1010101;
#10 address = 7'b1111001;
#10 address = 7'b1010101;
#10 address = 7'b1010111;
#10 address = 7'b1010111;



#50 $finish;
end


initial begin

  $dumpfile("Ejercicio5_tb.vcd");
  $dumpvars(0,testbench);
  end

endmodule

Lab9/Ejercicio5/Ejercicio5_tb.vcd
$date
	Sat Oct 31 10:18:55 2020
$end
$version
	Icarus Verilog
$end
$timescale
	1ps
$end
$scope module testbench $end
$var wire 13 ! data [12:0] $end
$var reg 7 " address [6:0] $end
$scope module M1 $end
$var wire 7 # address [6:0] $end
$var reg 13 $ data [12:0] $end
$upscope $end
$upscope $end
$enddefinitions $end
#0
$dumpvars
b1000000001000 $
bx0 #
bx0 "
b1000000001000 !
$end
#10
b100000001000 !
b100000001000 $
b1x1 "
b1x1 #
#20
b1000000001000 !
b1000000001000 $
b0x1 "
b0x1 #
#40
b11x1 "
b11x1 #
#50
b100000001000 !
b100000001000 $
b10x1 "
b10x1 #
#60
b1001000010 !
b1001000010 $
b10xx1 "
b10xx1 #
#70
b1001001100000 !
b1001001100000 $
b11xx1 "
b11xx1 #
#80
b11010000010 !
b11010000010 $
b100xx1 "
b100xx1 #
#90
b11010000100 !
b11010000100 $
b101xx1 "
b101xx1 #
#100
b1011010100000 !
b1011010100000 $
b110xx1 "
b110xx1 #
#110
b1000000111000 !
b1000000111000 $
b111xx1 "
b111xx1 #
#120
b100000001000 !
b100000001000 $
b1000x11 "
b1000x11 #
#130
b1000000001000 !
b1000000001000 $
b1000x01 "
b1000x01 #
#140
b1001x11 "
b1001x11 #
#150
b100000001000 !
b100000001000 $
b1001x01 "
b1001x01 #
#160
b11011000010 !
b11011000010 $
b1010xx1 "
b1010xx1 #
#170
b1011011100000 !
b1011011100000 $
b1011xx1 "
b1011xx1 #
#180
b100000001000 !
b100000001000 $
b1100xx1 "
b1100xx1 #
#190
b1001 !
b1001 $
b1101xx1 "
b1101xx1 #
#200
b11100000010 !
b11100000010 $
b1110xx1 "
b1110xx1 #
#210
b1011100100000 !
b1011100100000 $
b1111xx1 "
b1111xx1 #
#220
b0 !
b0 $
b1010101 "
b1010101 #
#230
b1111001 "
b1111001 #
#240
b1010101 "
b1010101 #
#250
b1010111 "
b1010111 #
