Lab8/Ejercicio3/Ejercicio3.v
//ejercicio 3
module alu(input [3:0] A, B, input [2:0] F,
           output [3:0] Y);

reg [3:0] salida_alu;
assign Y = salida_alu;

always @(*)
begin
  case(F)
  3'b000:
  salida_alu = A & B;
  3'b001:
  salida_alu = A | B;
  3'b010:
  salida_alu = A + B;
  3'b100:
  salida_alu = A & ~B;
  3'b101:
  salida_alu = A | ~B;
  3'b110:
  salida_alu = A - B;
  3'b111:
  salida_alu = (A<B?4'd1:4'd0);
  default salida_alu = A + B;
  endcase

end



endmodule

Lab8/Ejercicio3/Ejercicio3_tb.v
//ejercicio 3
module testbench();

reg [3:0] A, B;
reg [2:0] F;

wire [3:0] Y;

integer i;
alu a1(A,B,F,Y);

initial
begin
F = 3'b0;
A = 4'd2  ;
B= 4'd3;

for (i=0; i<=7;i=i+1)
begin
F = F + 3'd1;
#10;
end

A = 4'd2;
B= 4'd3;

end

initial begin
       $dumpfile("Ejercicio3_tb.vcd");
       $dumpvars(0,testbench);
   end

endmodule

Lab8/Ejercicio3/Ejercicio3_tb.vcd
$date
	Sat Oct 24 10:12:25 2020
$end
$version
	Icarus Verilog
$end
$timescale
	1ps
$end
$scope module testbench $end
$var wire 4 ! Y [3:0] $end
$var reg 4 " A [3:0] $end
$var reg 4 # B [3:0] $end
$var reg 3 $ F [2:0] $end
$var integer 32 % i [31:0] $end
$scope module a1 $end
$var wire 4 & A [3:0] $end
$var wire 4 ' B [3:0] $end
$var wire 3 ( F [2:0] $end
$var wire 4 ) Y [3:0] $end
$var reg 4 * salida_alu [3:0] $end
$upscope $end
$upscope $end
$enddefinitions $end
#0
$dumpvars
b11 *
b11 )
b1 (
b11 '
b10 &
b0 %
b1 $
b11 #
b10 "
b11 !
$end
#10
b101 !
b101 )
b101 *
b10 $
b10 (
b1 %
#20
b11 $
b11 (
b10 %
#30
b0 !
b0 )
b0 *
b100 $
b100 (
b11 %
#40
b1110 !
b1110 )
b1110 *
b101 $
b101 (
b100 %
#50
b1111 !
b1111 )
b1111 *
b110 $
b110 (
b101 %
#60
b1 !
b1 )
b1 *
b111 $
b111 (
b110 %
#70
b10 !
b10 )
b10 *
b0 $
b0 (
b111 %
#80
b1000 %
